Workbook
Name _DLX1.USE: #REF!
Name _Regression_Int: 1
Name a: #REF!
Name aa: #REF!
Name aaa: INDEX(#REF!,COUNTA(#REF!)-#REF!+1):INDEX(#REF!,COUNTA(#REF!))
Name ac: #REF!
Name asdfasdfasdfasdfasdfasdf: INDEX(#REF!,COUNTA(#REF!)-#REF!+1):INDEX(#REF!,COUNTA(#REF!))
Name b: #REF!
Name BHYDailyYield: OFFSET(#REF!,COUNTA(#REF!)-1,0,-254,1)
Name BLoansDailyYield: OFFSET(#REF!,COUNTA(#REF!)-1,0,-254,1)
Name Bond_Swap_Date: OFFSET(#REF!,COUNTA(#REF!)-1,0,-96,1)
Name Bond_Swap_Worst: OFFSET(#REF!,COUNTA(#REF!)-1,0,-96,1)
Name BR: #REF!
Name Business_Stat_Hist: OFFSET(#REF!,0,0,COUNTA(#REF!),5)
Name Ccy: #REF!
Name Chart_2: #REF!
Name CHART_9a: #REF!
Name CHART1: #REF!
Name CHART10: #REF!
Name Chart100: #REF!
Name chart11: #REF!
Name CHART12: #REF!
Name CHART13: #REF!
Name CHART14: #REF!
Name CHART15: #REF!
Name CHART16: #REF!
Name CHART2: #REF!
Name Chart2x: INDEX(#REF!,COUNTA(#REF!)-#REF!+1):INDEX(#REF!,COUNTA(#REF!))
Name CHART3: #REF!
Name Chart3x: #N/A
Name CHART4: #REF!
Name CHART5: #REF!
Name CHART6: #REF!
Name CHART7: #REF!
Name CHART8: #REF!
Name CHART9: #REF!
Name CHART9a: #REF!
Name clean_spreads: #REF!
Name CLPercent: INDEX(#REF!,COUNTA(#REF!)-#REF!+1):INDEX(#REF!,COUNTA(#REF!))
Name CLpercentYR: INDEX(#REF!,COUNTA(#REF!)-#REF!+1):INDEX(#REF!,COUNTA(#REF!))
Name CLQTR: #REF!
Name CLVolMN: #REF!
Name CLVolume: INDEX(#REF!,COUNTA(#REF!)-#REF!+1):INDEX(#REF!,COUNTA(#REF!))
Name CLVolumeYR: INDEX(#REF!,COUNTA(#REF!)-#REF!+1):INDEX(#REF!,COUNTA(#REF!))
Name CommercialExAIGMetrics: #REF!
Name Copyright: #REF!
Name CopyrightAnalytics: #REF!
Name CreatedFor: #REF!
Name CreatedForTitle: #REF!
Name CS_ALL: OFFSET(#REF!, COUNTA(#REF!)-1,0,-13,1)
Name CS_LBO: OFFSET(#REF!, COUNTA(#REF!)-1,0,-13,1)
Name CS_MA: OFFSET(#REF!, COUNTA(#REF!)-1,0,-13,1)
Name CS_Period: OFFSET(#REF!, COUNTA(#REF!)-1,0,-13,1)
Name Currency_Table: OFFSET(#REF!,0,0,COUNTA(#REF!)-1,5)
Name Currency_Table2: OFFSET(#REF!,0,0,COUNTA(#REF!)-1,5)
Name Currency_Table3: OFFSET(#REF!,0,0,COUNTA(#REF!)-1,5)
Name CurrencyInput: #REF!
Name d: #REF!
Name dasdfasdfasdf: INDEX(#REF!,COUNTA(#REF!)-#REF!+1):INDEX(#REF!,COUNTA(#REF!))
Name Date: OFFSET(#REF!,COUNTA(#REF!)-1,0,-47,1)

Sheet fund_performance
A1: fund_id | B1: month_end | C1: sgg_nav | D1: sgg_nav_source | E1: nav | F1: nav_source | G1: nav_per_share | H1: nav_per_share_source | I1: distributions_per_share | J1: distributions_per_share_source | K1: monthly_return | L1: monthly_return_source | M1: nport_portfolio_count | N1: gav | O1: gav_source | P1: shares_outstanding | Q1: shares_outstanding_source | R1: shares_owned | S1: shares_owned_source | T1: sgg_purchases | U1: sgg_purchases_source | V1: sgg_redemptions | W1: sgg_redemptions_source | X1: sgg_distributions | Y1: sgg_distributions_source | Z1: gp_count | AA1: gp_count_source | AB1: fund_name | AC1: strategy
A2: 1 | B2: 46173 | G2: 55.56 | H2: pitchbook | AB2: =IFERROR(VLOOKUP($A2,fund_metadata!$A:$P,2,FALSE),"") -> Bow River Evergreen PE | AC2: =IFERROR(VLOOKUP($A2,fund_metadata!$A:$P,16,FALSE),"") -> private_equity
A3: 1 | B3: 46142 | C3: 5132009.8 | D3: black diamond | E3: 1240000000 | F3: pitchbook | G3: 55.17 | H3: pitchbook | K3: 0.0034 | L3: pitchbook | AB3: =IFERROR(VLOOKUP($A3,fund_metadata!$A:$P,2,FALSE),"") -> Bow River Evergreen PE | AC3: =IFERROR(VLOOKUP($A3,fund_metadata!$A:$P,16,FALSE),"") -> private_equity
A4: 1 | B4: 46112 | C4: 5114594.6 | D4: direct fund statement | E4: 1220000000 | F4: pitchbook | G4: 54.98 | H4: pitchbook | K4: 0.0039 | L4: pitchbook | M4: 198 | R4: 93030.179 | S4: direct fund statement | T4: 0 | U4: direct fund statement | V4: 0 | W4: direct fund statement | X4: 0 | Y4: direct fund statement | AB4: =IFERROR(VLOOKUP($A4,fund_metadata!$A:$P,2,FALSE),"") -> Bow River Evergreen PE | AC4: =IFERROR(VLOOKUP($A4,fund_metadata!$A:$P,16,FALSE),"") -> private_equity
A5: 1 | B5: 46081 | C5: 5094704.7 | D5: direct fund statement | E5: 1190000000 | F5: pitchbook | G5: 54.76 | H5: pitchbook | K5: 0.0069 | L5: pitchbook | R5: 93030.179 | S5: direct fund statement | T5: 0 | U5: direct fund statement | V5: 0 | W5: direct fund statement | X5: 0 | Y5: direct fund statement | AB5: =IFERROR(VLOOKUP($A5,fund_metadata!$A:$P,2,FALSE),"") -> Bow River Evergreen PE | AC5: =IFERROR(VLOOKUP($A5,fund_metadata!$A:$P,16,FALSE),"") -> private_equity
A6: 1 | B6: 46053 | C6: 5059902.1 | D6: direct fund statement | E6: 1160000000 | F6: pitchbook | G6: 54.39 | H6: pitchbook | K6: 0.012 | L6: pitchbook | R6: 93030.179 | S6: direct fund statement | T6: 5000000 | U6: direct fund statement | V6: 0 | W6: direct fund statement | X6: 0 | Y6: direct fund statement | AB6: =IFERROR(VLOOKUP($A6,fund_metadata!$A:$P,2,FALSE),"") -> Bow River Evergreen PE | AC6: =IFERROR(VLOOKUP($A6,fund_metadata!$A:$P,16,FALSE),"") -> private_equity
A7: 1 | B7: 46022 | E7: 1120000000 | F7: pitchbook | G7: 53.75 | H7: pitchbook | K7: -0.0113 | L7: pitchbook | M7: 185 | AB7: =IFERROR(VLOOKUP($A7,fund_metadata!$A:$P,2,FALSE),"") -> Bow River Evergreen PE | AC7: =IFERROR(VLOOKUP($A7,fund_metadata!$A:$P,16,FALSE),"") -> private_equity
A8: 1 | B8: 45991 | E8: 1090000000 | F8: pitchbook | G8: 54.36 | H8: pitchbook | K8: 0.0319 | L8: pitchbook | AB8: =IFERROR(VLOOKUP($A8,fund_metadata!$A:$P,2,FALSE),"") -> Bow River Evergreen PE | AC8: =IFERROR(VLOOKUP($A8,fund_metadata!$A:$P,16,FALSE),"") -> private_equity
A9: 1 | B9: 45961 | E9: 1050000000 | F9: pitchbook | G9: 52.68 | H9: pitchbook | K9: 0.0125 | L9: pitchbook | AB9: =IFERROR(VLOOKUP($A9,fund_metadata!$A:$P,2,FALSE),"") -> Bow River Evergreen PE | AC9: =IFERROR(VLOOKUP($A9,fund_metadata!$A:$P,16,FALSE),"") -> private_equity
A10: 1 | B10: 45930 | E10: 1000000000 | F10: pitchbook | G10: 52.03 | H10: pitchbook | K10: 0.0066 | L10: pitchbook | M10: 176 | N10: 1040000000 | O10: pitchbook | P10: 18405421 | Q10: N-CSRS | AB10: =IFERROR(VLOOKUP($A10,fund_metadata!$A:$P,2,FALSE),"") -> Bow River Evergreen PE | AC10: =IFERROR(VLOOKUP($A10,fund_metadata!$A:$P,16,FALSE),"") -> private_equity
A11: 1 | B11: 45900 | E11: 942530000 | F11: pitchbook | G11: 51.69 | H11: pitchbook | K11: 0.0191 | L11: pitchbook | AB11: =IFERROR(VLOOKUP($A11,fund_metadata!$A:$P,2,FALSE),"") -> Bow River Evergreen PE | AC11: =IFERROR(VLOOKUP($A11,fund_metadata!$A:$P,16,FALSE),"") -> private_equity
A12: 1 | B12: 45869 | E12: 894140000 | F12: pitchbook | G12: 50.72 | H12: pitchbook | K12: -0.002 | L12: pitchbook | AB12: =IFERROR(VLOOKUP($A12,fund_metadata!$A:$P,2,FALSE),"") -> Bow River Evergreen PE | AC12: =IFERROR(VLOOKUP($A12,fund_metadata!$A:$P,16,FALSE),"") -> private_equity
A13: 1 | B13: 45838 | E13: 849670000 | F13: pitchbook | G13: 50.82 | H13: pitchbook | I13: 0 | J13: yfinance | K13: 0.0004 | L13: pitchbook | M13: 157 | AB13: =IFERROR(VLOOKUP($A13,fund_metadata!$A:$P,2,FALSE),"") -> Bow River Evergreen PE | AC13: =IFERROR(VLOOKUP($A13,fund_metadata!$A:$P,16,FALSE),"") -> private_equity
A14: 1 | B14: 45808 | E14: 826540000 | F14: pitchbook | G14: 50.8 | H14: pitchbook | I14: 0 | J14: yfinance | K14: 0.0142 | L14: pitchbook | AB14: =IFERROR(VLOOKUP($A14,fund_metadata!$A:$P,2,FALSE),"") -> Bow River Evergreen PE | AC14: =IFERROR(VLOOKUP($A14,fund_metadata!$A:$P,16,FALSE),"") -> private_equity
A15: 1 | B15: 45777 | E15: 807000000 | F15: pitchbook | G15: 50.09 | H15: pitchbook | I15: 0 | J15: yfinance | K15: 0.0081 | L15: pitchbook | AB15: =IFERROR(VLOOKUP($A15,fund_metadata!$A:$P,2,FALSE),"") -> Bow River Evergreen PE | AC15: =IFERROR(VLOOKUP($A15,fund_metadata!$A:$P,16,FALSE),"") -> private_equity
A16: 1 | B16: 45747 | E16: 774220000 | F16: pitchbook | G16: 49.69 | H16: pitchbook | I16: 0 | J16: yfinance | K16: 0.0182 | L16: pitchbook | M16: 147 | N16: 817800000 | O16: pitchbook | P16: 14550293 | Q16: N-CSR | AB16: =IFERROR(VLOOKUP($A16,fund_metadata!$A:$P,2,FALSE),"") -> Bow River Evergreen PE | AC16: =IFERROR(VLOOKUP($A16,fund_metadata!$A:$P,16,FALSE),"") -> private_equity
A17: 1 | B17: 45716 | E17: 735550000 | F17: pitchbook | G17: 48.8 | H17: pitchbook | I17: 0 | J17: yfinance | K17: 0.0215 | L17: pitchbook | AB17: =IFERROR(VLOOKUP($A17,fund_metadata!$A:$P,2,FALSE),"") -> Bow River Evergreen PE | AC17: =IFERROR(VLOOKUP($A17,fund_metadata!$A:$P,16,FALSE),"") -> private_equity
A18: 1 | B18: 45688 | E18: 701580000 | F18: pitchbook | G18: 47.77 | H18: pitchbook | I18: 0 | J18: yfinance | K18: 0.005 | L18: pitchbook | AB18: =IFERROR(VLOOKUP($A18,fund_metadata!$A:$P,2,FALSE),"") -> Bow River Evergreen PE | AC18: =IFERROR(VLOOKUP($A18,fund_metadata!$A:$P,16,FALSE),"") -> private_equity
A19: 1 | B19: 45657 | E19: 669420000 | F19: pitchbook | G19: 47.54 | H19: pitchbook | I19: 1.137 | J19: yfinance | K19: 0.004 | L19: pitchbook | M19: 142 | AB19: =IFERROR(VLOOKUP($A19,fund_metadata!$A:$P,2,FALSE),"") -> Bow River Evergreen PE | AC19: =IFERROR(VLOOKUP($A19,fund_metadata!$A:$P,16,FALSE),"") -> private_equity
A20: 1 | B20: 45626 | E20: 658210000 | F20: pitchbook | G20: 48.48 | H20: pitchbook | I20: 0 | J20: yfinance | K20: 0.0115 | L20: pitchbook | AB20: =IFERROR(VLOOKUP($A20,fund_metadata!$A:$P,2,FALSE),"") -> Bow River Evergreen PE | AC20: =IFERROR(VLOOKUP($A20,fund_metadata!$A:$P,16,FALSE),"") -> private_equity
A21: 1 | B21: 45596 | E21: 633880000 | F21: pitchbook | G21: 47.94 | H21: pitchbook | I21: 0 | J21: yfinance | K21: 0.0028 | L21: pitchbook | AB21: =IFERROR(VLOOKUP($A21,fund_metadata!$A:$P,2,FALSE),"") -> Bow River Evergreen PE | AC21: =IFERROR(VLOOKUP($A21,fund_metadata!$A:$P,16,FALSE),"") -> private_equity
A22: 1 | B22: 45565 | E22: 617640000 | F22: pitchbook | G22: 47.8 | H22: pitchbook | I22: 0 | J22: yfinance | K22: 0.0119 | L22: pitchbook | M22: 131 | N22: 632440000 | O22: pitchbook | P22: 12219603 | Q22: N-CSRS | AB22: =IFERROR(VLOOKUP($A22,fund_metadata!$A:$P,2,FALSE),"") -> Bow River Evergreen PE | AC22: =IFERROR(VLOOKUP($A22,fund_metadata!$A:$P,16,FALSE),"") -> private_equity
A23: 1 | B23: 45535 | E23: 600190000 | F23: pitchbook | G23: 47.24 | H23: pitchbook | I23: 0 | J23: yfinance | K23: 0.029 | L23: pitchbook | AB23: =IFERROR(VLOOKUP($A23,fund_metadata!$A:$P,2,FALSE),"") -> Bow River Evergreen PE | AC23: =IFERROR(VLOOKUP($A23,fund_metadata!$A:$P,16,FALSE),"") -> private_equity
A24: 1 | B24: 45504 | E24: 565090000 | F24: pitchbook | G24: 45.9 | H24: pitchbook | I24: 0 | J24: yfinance | K24: 0.0011 | L24: pitchbook | AB24: =IFERROR(VLOOKUP($A24,fund_metadata!$A:$P,2,FALSE),"") -> Bow River Evergreen PE | AC24: =IFERROR(VLOOKUP($A24,fund_metadata!$A:$P,16,FALSE),"") -> private_equity
A25: 1 | B25: 45473 | E25: 552750000 | F25: pitchbook | G25: 45.85 | H25: pitchbook | I25: 0 | J25: yfinance | K25: 0.0004 | L25: pitchbook | M25: 121 | AB25: =IFERROR(VLOOKUP($A25,fund_metadata!$A:$P,2,FALSE),"") -> Bow River Evergreen PE | AC25: =IFERROR(VLOOKUP($A25,fund_metadata!$A:$P,16,FALSE),"") -> private_equity
A26: 1 | B26: 45443 | E26: 530130000 | F26: pitchbook | G26: 45.83 | H26: pitchbook | K26: 0.0212 | L26: pitchbook | AB26: =IFERROR(VLOOKUP($A26,fund_metadata!$A:$P,2,FALSE),"") -> Bow River Evergreen PE | AC26: =IFERROR(VLOOKUP($A26,fund_metadata!$A:$P,16,FALSE),"") -> private_equity
A27: 1 | B27: 45412 | E27: 509290000 | F27: pitchbook | G27: 44.88 | H27: pitchbook | K27: 0.0134 | L27: pitchbook | AB27: =IFERROR(VLOOKUP($A27,fund_metadata!$A:$P,2,FALSE),"") -> Bow River Evergreen PE | AC27: =IFERROR(VLOOKUP($A27,fund_metadata!$A:$P,16,FALSE),"") -> private_equity
A28: 1 | B28: 45382 | E28: 486790000 | F28: pitchbook | G28: 44.29 | H28: pitchbook | K28: 0.0082 | L28: pitchbook | M28: 112 | N28: 519920000 | O28: pitchbook | P28: 10327322 | Q28: N-CSR | AB28: =IFERROR(VLOOKUP($A28,fund_metadata!$A:$P,2,FALSE),"") -> Bow River Evergreen PE | AC28: =IFERROR(VLOOKUP($A28,fund_metadata!$A:$P,16,FALSE),"") -> private_equity
A29: 1 | B29: 45351 | E29: 476530000 | F29: pitchbook | G29: 43.93 | H29: pitchbook | K29: 0.0131 | L29: pitchbook | AB29: =IFERROR(VLOOKUP($A29,fund_metadata!$A:$P,2,FALSE),"") -> Bow River Evergreen PE | AC29: =IFERROR(VLOOKUP($A29,fund_metadata!$A:$P,16,FALSE),"") -> private_equity
A30: 1 | B30: 45322 | E30: 459740000 | F30: pitchbook | G30: 43.36 | H30: pitchbook | K30: -0.0002 | L30: pitchbook | AB30: =IFERROR(VLOOKUP($A30,fund_metadata!$A:$P,2,FALSE),"") -> Bow River Evergreen PE | AC30: =IFERROR(VLOOKUP($A30,fund_metadata!$A:$P,16,FALSE),"") -> private_equity
A31: 1 | B31: 45291 | E31: 446350000 | F31: pitchbook | G31: 43.37 | H31: pitchbook | K31: 0.0018 | L31: pitchbook | M31: 106 | AB31: =IFERROR(VLOOKUP($A31,fund_metadata!$A:$P,2,FALSE),"") -> Bow River Evergreen PE | AC31: =IFERROR(VLOOKUP($A31,fund_metadata!$A:$P,16,FALSE),"") -> private_equity
A32: 1 | B32: 45260 | E32: 438230000 | F32: pitchbook | G32: 43.98 | H32: pitchbook | K32: 0.012 | L32: pitchbook | AB32: =IFERROR(VLOOKUP($A32,fund_metadata!$A:$P,2,FALSE),"") -> Bow River Evergreen PE | AC32: =IFERROR(VLOOKUP($A32,fund_metadata!$A:$P,16,FALSE),"") -> private_equity
A33: 1 | B33: 45230 | E33: 427670000 | F33: pitchbook | G33: 43.45 | H33: pitchbook | K33: 0.0371 | L33: pitchbook | AB33: =IFERROR(VLOOKUP($A33,fund_metadata!$A:$P,2,FALSE),"") -> Bow River Evergreen PE | AC33: =IFERROR(VLOOKUP($A33,fund_metadata!$A:$P,16,FALSE),"") -> private_equity
A34: 1 | B34: 45199 | E34: 400100000 | F34: pitchbook | G34: 41.9 | H34: pitchbook | K34: -0.0023 | L34: pitchbook | M34: 105 | N34: 412100000 | O34: pitchbook | P34: 8965808 | Q34: N-CSRS | AB34: =IFERROR(VLOOKUP($A34,fund_metadata!$A:$P,2,FALSE),"") -> Bow River Evergreen PE | AC34: =IFERROR(VLOOKUP($A34,fund_metadata!$A:$P,16,FALSE),"") -> private_equity
A35: 1 | B35: 45169 | E35: 395660000 | F35: pitchbook | G35: 42 | H35: pitchbook | K35: 0.0206 | L35: pitchbook | AB35: =IFERROR(VLOOKUP($A35,fund_metadata!$A:$P,2,FALSE),"") -> Bow River Evergreen PE | AC35: =IFERROR(VLOOKUP($A35,fund_metadata!$A:$P,16,FALSE),"") -> private_equity
A36: 1 | B36: 45138 | E36: 380550000 | F36: pitchbook | G36: 41.15 | H36: pitchbook | K36: 0.0113 | L36: pitchbook | AB36: =IFERROR(VLOOKUP($A36,fund_metadata!$A:$P,2,FALSE),"") -> Bow River Evergreen PE | AC36: =IFERROR(VLOOKUP($A36,fund_metadata!$A:$P,16,FALSE),"") -> private_equity
A37: 1 | B37: 45107 | E37: 369270000 | F37: pitchbook | G37: 40.69 | H37: pitchbook | K37: 0.0068 | L37: pitchbook | M37: 98 | AB37: =IFERROR(VLOOKUP($A37,fund_metadata!$A:$P,2,FALSE),"") -> Bow River Evergreen PE | AC37: =IFERROR(VLOOKUP($A37,fund_metadata!$A:$P,16,FALSE),"") -> private_equity
A38: 1 | B38: 45077 | E38: 357990000 | F38: pitchbook | G38: 40.41 | H38: pitchbook | K38: 0.0002 | L38: pitchbook | AB38: =IFERROR(VLOOKUP($A38,fund_metadata!$A:$P,2,FALSE),"") -> Bow River Evergreen PE | AC38: =IFERROR(VLOOKUP($A38,fund_metadata!$A:$P,16,FALSE),"") -> private_equity
A39: 1 | B39: 45046 | E39: 352740000 | F39: pitchbook | G39: 40.41 | H39: pitchbook | K39: 0.0078 | L39: pitchbook | AB39: =IFERROR(VLOOKUP($A39,fund_metadata!$A:$P,2,FALSE),"") -> Bow River Evergreen PE | AC39: =IFERROR(VLOOKUP($A39,fund_metadata!$A:$P,16,FALSE),"") -> private_equity
A40: 1 | B40: 45016 | E40: 341380000 | F40: pitchbook | G40: 40.09 | H40: pitchbook | K40: 0.0038 | L40: pitchbook | M40: 98 | N40: 353810000 | O40: pitchbook | AB40: =IFERROR(VLOOKUP($A40,fund_metadata!$A:$P,2,FALSE),"") -> Bow River Evergreen PE | AC40: =IFERROR(VLOOKUP($A40,fund_metadata!$A:$P,16,FALSE),"") -> private_equity
A41: 1 | B41: 44985 | E41: 325700000 | F41: pitchbook | G41: 39.94 | H41: pitchbook | K41: 0.0141 | L41: pitchbook | AB41: =IFERROR(VLOOKUP($A41,fund_metadata!$A:$P,2,FALSE),"") -> Bow River Evergreen PE | AC41: =IFERROR(VLOOKUP($A41,fund_metadata!$A:$P,16,FALSE),"") -> private_equity
A42: 1 | B42: 44957 | E42: 314370000 | F42: pitchbook | G42: 39.39 | H42: pitchbook | K42: 0.0001 | L42: pitchbook | AB42: =IFERROR(VLOOKUP($A42,fund_metadata!$A:$P,2,FALSE),"") -> Bow River Evergreen PE | AC42: =IFERROR(VLOOKUP($A42,fund_metadata!$A:$P,16,FALSE),"") -> private_equity
A43: 1 | B43: 44926 | E43: 299140000 | F43: pitchbook | G43: 39.39 | H43: pitchbook | K43: 0.0081 | L43: pitchbook | M43: 96 | AB43: =IFERROR(VLOOKUP($A43,fund_metadata!$A:$P,2,FALSE),"") -> Bow River Evergreen PE | AC43: =IFERROR(VLOOKUP($A43,fund_metadata!$A:$P,16,FALSE),"") -> private_equity
A44: 1 | B44: 44895 | E44: 296020000 | F44: pitchbook | G44: 40.18 | H44: pitchbook | K44: 0.0107 | L44: pitchbook | AB44: =IFERROR(VLOOKUP($A44,fund_metadata!$A:$P,2,FALSE),"") -> Bow River Evergreen PE | AC44: =IFERROR(VLOOKUP($A44,fund_metadata!$A:$P,16,FALSE),"") -> private_equity
A45: 1 | B45: 44865 | E45: 286020000 | F45: pitchbook | G45: 39.75 | H45: pitchbook | K45: -0.003 | L45: pitchbook | AB45: =IFERROR(VLOOKUP($A45,fund_metadata!$A:$P,2,FALSE),"") -> Bow River Evergreen PE | AC45: =IFERROR(VLOOKUP($A45,fund_metadata!$A:$P,16,FALSE),"") -> private_equity
A46: 1 | B46: 44834 | E46: 279610000 | F46: pitchbook | G46: 39.87 | H46: pitchbook | K46: -0.0018 | L46: pitchbook | M46: 88 | N46: 292180000 | O46: pitchbook | P46: 6459606 | Q46: N-CSRS | AB46: =IFERROR(VLOOKUP($A46,fund_metadata!$A:$P,2,FALSE),"") -> Bow River Evergreen PE | AC46: =IFERROR(VLOOKUP($A46,fund_metadata!$A:$P,16,FALSE),"") -> private_equity
A47: 1 | B47: 44804 | E47: 269150000 | F47: pitchbook | G47: 39.94 | H47: pitchbook | K47: 0.0045 | L47: pitchbook | AB47: =IFERROR(VLOOKUP($A47,fund_metadata!$A:$P,2,FALSE),"") -> Bow River Evergreen PE | AC47: =IFERROR(VLOOKUP($A47,fund_metadata!$A:$P,16,FALSE),"") -> private_equity
A48: 1 | B48: 44773 | E48: 257890000 | F48: pitchbook | G48: 39.76 | H48: pitchbook | K48: -0.0039 | L48: pitchbook | AB48: =IFERROR(VLOOKUP($A48,fund_metadata!$A:$P,2,FALSE),"") -> Bow River Evergreen PE | AC48: =IFERROR(VLOOKUP($A48,fund_metadata!$A:$P,16,FALSE),"") -> private_equity
A49: 1 | B49: 44742 | E49: 247830000 | F49: pitchbook | G49: 39.92 | H49: pitchbook | K49: -0.0053 | L49: pitchbook | M49: 79 | AB49: =IFERROR(VLOOKUP($A49,fund_metadata!$A:$P,2,FALSE),"") -> Bow River Evergreen PE | AC49: =IFERROR(VLOOKUP($A49,fund_metadata!$A:$P,16,FALSE),"") -> private_equity
A50: 1 | B50: 44712 | E50: 238290000 | F50: pitchbook | G50: 40.13 | H50: pitchbook | K50: 0.0114 | L50: pitchbook | AB50: =IFERROR(VLOOKUP($A50,fund_metadata!$A:$P,2,FALSE),"") -> Bow River Evergreen PE | AC50: =IFERROR(VLOOKUP($A50,fund_metadata!$A:$P,16,FALSE),"") -> private_equity
A51: 1 | B51: 44681 | E51: 227980000 | F51: pitchbook | G51: 39.68 | H51: pitchbook | K51: 0.0045 | L51: pitchbook | AB51: =IFERROR(VLOOKUP($A51,fund_metadata!$A:$P,2,FALSE),"") -> Bow River Evergreen PE | AC51: =IFERROR(VLOOKUP($A51,fund_metadata!$A:$P,16,FALSE),"") -> private_equity
A52: 1 | B52: 44651 | E52: 217280000 | F52: pitchbook | G52: 39.5 | H52: pitchbook | K52: 0.0232 | L52: pitchbook | M52: 64 | N52: 230020000 | O52: pitchbook | P52: 5341595 | Q52: N-CSR | AB52: =IFERROR(VLOOKUP($A52,fund_metadata!$A:$P,2,FALSE),"") -> Bow River Evergreen PE | AC52: =IFERROR(VLOOKUP($A52,fund_metadata!$A:$P,16,FALSE),"") -> private_equity
A53: 1 | B53: 44620 | E53: 206170000 | F53: pitchbook | G53: 38.6 | H53: pitchbook | K53: 0.0157 | L53: pitchbook | AB53: =IFERROR(VLOOKUP($A53,fund_metadata!$A:$P,2,FALSE),"") -> Bow River Evergreen PE | AC53: =IFERROR(VLOOKUP($A53,fund_metadata!$A:$P,16,FALSE),"") -> private_equity
A54: 1 | B54: 44592 | E54: 191620000 | F54: pitchbook | G54: 38.01 | H54: pitchbook | K54: -0.0097 | L54: pitchbook | AB54: =IFERROR(VLOOKUP($A54,fund_metadata!$A:$P,2,FALSE),"") -> Bow River Evergreen PE | AC54: =IFERROR(VLOOKUP($A54,fund_metadata!$A:$P,16,FALSE),"") -> private_equity
A55: 1 | B55: 44561 | E55: 181180000 | F55: pitchbook | G55: 38.38 | H55: pitchbook | K55: 0.0063 | L55: pitchbook | M55: 53 | AB55: =IFERROR(VLOOKUP($A55,fund_metadata!$A:$P,2,FALSE),"") -> Bow River Evergreen PE | AC55: =IFERROR(VLOOKUP($A55,fund_metadata!$A:$P,16,FALSE),"") -> private_equity
A56: 1 | B56: 44530 | E56: 172670000 | F56: pitchbook | G56: 38.41 | H56: pitchbook | K56: 0.0449 | L56: pitchbook | AB56: =IFERROR(VLOOKUP($A56,fund_metadata!$A:$P,2,FALSE),"") -> Bow River Evergreen PE | AC56: =IFERROR(VLOOKUP($A56,fund_metadata!$A:$P,16,FALSE),"") -> private_equity
A57: 1 | B57: 44500 | E57: 152780000 | F57: pitchbook | G57: 36.76 | H57: pitchbook | K57: 0.0004 | L57: pitchbook | AB57: =IFERROR(VLOOKUP($A57,fund_metadata!$A:$P,2,FALSE),"") -> Bow River Evergreen PE | AC57: =IFERROR(VLOOKUP($A57,fund_metadata!$A:$P,16,FALSE),"") -> private_equity
A58: 1 | B58: 44469 | E58: 150110000 | F58: pitchbook | G58: 36.75 | H58: pitchbook | K58: 0.0204 | L58: pitchbook | M58: 46 | P58: 4085205 | Q58: N-CSRS | AB58: =IFERROR(VLOOKUP($A58,fund_metadata!$A:$P,2,FALSE),"") -> Bow River Evergreen PE | AC58: =IFERROR(VLOOKUP($A58,fund_metadata!$A:$P,16,FALSE),"") -> private_equity
A59: 1 | B59: 44439 | E59: 141200000 | F59: pitchbook | G59: 36.01 | H59: pitchbook | K59: 0.0432 | L59: pitchbook | AB59: =IFERROR(VLOOKUP($A59,fund_metadata!$A:$P,2,FALSE),"") -> Bow River Evergreen PE | AC59: =IFERROR(VLOOKUP($A59,fund_metadata!$A:$P,16,FALSE),"") -> private_equity
A60: 1 | B60: 44408 | E60: 131660000 | F60: pitchbook | G60: 34.52 | H60: pitchbook | K60: 0.02 | L60: pitchbook | AB60: =IFERROR(VLOOKUP($A60,fund_metadata!$A:$P,2,FALSE),"") -> Bow River Evergreen PE | AC60: =IFERROR(VLOOKUP($A60,fund_metadata!$A:$P,16,FALSE),"") -> private_equity
A61: 1 | B61: 44377 | E61: 127850000 | F61: pitchbook | G61: 33.84 | H61: pitchbook | K61: 0.0242 | L61: pitchbook | M61: 40 | AB61: =IFERROR(VLOOKUP($A61,fund_metadata!$A:$P,2,FALSE),"") -> Bow River Evergreen PE | AC61: =IFERROR(VLOOKUP($A61,fund_metadata!$A:$P,16,FALSE),"") -> private_equity
A62: 1 | B62: 44347 | G62: 33.04 | H62: pitchbook | K62: 0.0394 | L62: pitchbook | AB62: =IFERROR(VLOOKUP($A62,fund_metadata!$A:$P,2,FALSE),"") -> Bow River Evergreen PE | AC62: =IFERROR(VLOOKUP($A62,fund_metadata!$A:$P,16,FALSE),"") -> private_equity
A63: 1 | B63: 44316 | G63: 31.79 | H63: pitchbook | K63: 0.0007 | L63: pitchbook | AB63: =IFERROR(VLOOKUP($A63,fund_metadata!$A:$P,2,FALSE),"") -> Bow River Evergreen PE | AC63: =IFERROR(VLOOKUP($A63,fund_metadata!$A:$P,16,FALSE),"") -> private_equity
A64: 1 | B64: 44286 | G64: 31.77 | H64: pitchbook | K64: 0.0186 | L64: pitchbook | M64: 32 | P64: 2869318 | Q64: N-CSR | AB64: =IFERROR(VLOOKUP($A64,fund_metadata!$A:$P,2,FALSE),"") -> Bow River Evergreen PE | AC64: =IFERROR(VLOOKUP($A64,fund_metadata!$A:$P,16,FALSE),"") -> private_equity
A65: 1 | B65: 44255 | G65: 31.19 | H65: pitchbook | K65: 0.0264 | L65: pitchbook | AB65: =IFERROR(VLOOKUP($A65,fund_metadata!$A:$P,2,FALSE),"") -> Bow River Evergreen PE | AC65: =IFERROR(VLOOKUP($A65,fund_metadata!$A:$P,16,FALSE),"") -> private_equity
A66: 1 | B66: 44227 | G66: 30.39 | H66: pitchbook | K66: 0.0273 | L66: pitchbook | AB66: =IFERROR(VLOOKUP($A66,fund_metadata!$A:$P,2,FALSE),"") -> Bow River Evergreen PE | AC66: =IFERROR(VLOOKUP($A66,fund_metadata!$A:$P,16,FALSE),"") -> private_equity
A67: 1 | B67: 44196 | G67: 29.58 | H67: pitchbook | K67: -0.0008 | L67: pitchbook | AB67: =IFERROR(VLOOKUP($A67,fund_metadata!$A:$P,2,FALSE),"") -> Bow River Evergreen PE | AC67: =IFERROR(VLOOKUP($A67,fund_metadata!$A:$P,16,FALSE),"") -> private_equity
A68: 1 | B68: 44165 | G68: 29.6 | H68: pitchbook | K68: 0.0118 | L68: pitchbook | AB68: =IFERROR(VLOOKUP($A68,fund_metadata!$A:$P,2,FALSE),"") -> Bow River Evergreen PE | AC68: =IFERROR(VLOOKUP($A68,fund_metadata!$A:$P,16,FALSE),"") -> private_equity
A69: 1 | B69: 44135 | G69: 29.26 | H69: pitchbook | K69: 0.0001 | L69: pitchbook | AB69: =IFERROR(VLOOKUP($A69,fund_metadata!$A:$P,2,FALSE),"") -> Bow River Evergreen PE | AC69: =IFERROR(VLOOKUP($A69,fund_metadata!$A:$P,16,FALSE),"") -> private_equity
A70: 1 | B70: 44104 | G70: 29.26 | H70: pitchbook | K70: 0.0149 | L70: pitchbook | AB70: =IFERROR(VLOOKUP($A70,fund_metadata!$A:$P,2,FALSE),"") -> Bow River Evergreen PE | AC70: =IFERROR(VLOOKUP($A70,fund_metadata!$A:$P,16,FALSE),"") -> private_equity
A71: 1 | B71: 44074 | G71: 28.83 | H71: pitchbook | K71: 0.0016 | L71: pitchbook | AB71: =IFERROR(VLOOKUP($A71,fund_metadata!$A:$P,2,FALSE),"") -> Bow River Evergreen PE | AC71: =IFERROR(VLOOKUP($A71,fund_metadata!$A:$P,16,FALSE),"") -> private_equity
A72: 1 | B72: 44043 | G72: 28.78 | H72: pitchbook | K72: 0.0026 | L72: pitchbook | AB72: =IFERROR(VLOOKUP($A72,fund_metadata!$A:$P,2,FALSE),"") -> Bow River Evergreen PE | AC72: =IFERROR(VLOOKUP($A72,fund_metadata!$A:$P,16,FALSE),"") -> private_equity
A73: 1 | B73: 44012 | G73: 28.71 | H73: pitchbook | K73: 0.1024 | L73: pitchbook | AB73: =IFERROR(VLOOKUP($A73,fund_metadata!$A:$P,2,FALSE),"") -> Bow River Evergreen PE | AC73: =IFERROR(VLOOKUP($A73,fund_metadata!$A:$P,16,FALSE),"") -> private_equity
A74: 1 | B74: 43982 | G74: 26.04 | H74: pitchbook | AB74: =IFERROR(VLOOKUP($A74,fund_metadata!$A:$P,2,FALSE),"") -> Bow River Evergreen PE | AC74: =IFERROR(VLOOKUP($A74,fund_metadata!$A:$P,16,FALSE),"") -> private_equity
A75: 8 | B75: 46173 | AB75: =IFERROR(VLOOKUP($A75,fund_metadata!$A:$P,2,FALSE),"") -> AMG Pantheon | AC75: =IFERROR(VLOOKUP($A75,fund_metadata!$A:$P,16,FALSE),"") -> secondaries
A76: 8 | B76: 46142 | G76: 28.53 | H76: pitchbook | K76: 0.0113 | L76: pitchbook | AB76: =IFERROR(VLOOKUP($A76,fund_metadata!$A:$P,2,FALSE),"") -> AMG Pantheon | AC76: =IFERROR(VLOOKUP($A76,fund_metadata!$A:$P,16,FALSE),"") -> secondaries
A77: 8 | B77: 46112 | C77: 9989376.8 | D77: icapital | G77: 28.21 | H77: pitchbook | K77: -0.0039 | L77: pitchbook | M77: 1 | R77: 354107.65 | S77: icapital | T77: 0 | U77: morgan stanley statement | V77: 0 | W77: morgan stanley statement | X77: 0 | Y77: morgan stanley statement | AB77: =IFERROR(VLOOKUP($A77,fund_metadata!$A:$P,2,FALSE),"") -> AMG Pantheon | AC77: =IFERROR(VLOOKUP($A77,fund_metadata!$A:$P,16,FALSE),"") -> secondaries
A78: 8 | B78: 46081 | C78: 10028329 | D78: icapital | G78: 28.32 | H78: pitchbook | K78: 0.0068 | L78: pitchbook | R78: 354107.65 | S78: icapital | T78: 0 | U78: morgan stanley statement | V78: 0 | W78: morgan stanley statement | X78: 0 | Y78: morgan stanley statement | AB78: =IFERROR(VLOOKUP($A78,fund_metadata!$A:$P,2,FALSE),"") -> AMG Pantheon | AC78: =IFERROR(VLOOKUP($A78,fund_metadata!$A:$P,16,FALSE),"") -> secondaries
A79: 8 | B79: 46053 | C79: 9961048.2 | D79: icapital | G79: 28.13 | H79: pitchbook | K79: -0.0039 | L79: pitchbook | R79: 354107.65 | S79: icapital | T79: 10000000 | U79: morgan stanley statement | V79: 0 | W79: morgan stanley statement | X79: 0 | Y79: morgan stanley statement | AB79: =IFERROR(VLOOKUP($A79,fund_metadata!$A:$P,2,FALSE),"") -> AMG Pantheon | AC79: =IFERROR(VLOOKUP($A79,fund_metadata!$A:$P,16,FALSE),"") -> secondaries
A80: 8 | B80: 46022 | C80: 10000000 | D80: black diamond | G80: 28.24 | H80: pitchbook | K80: 0.012 | L80: pitchbook | M80: 1 | AB80: =IFERROR(VLOOKUP($A80,fund_metadata!$A:$P,2,FALSE),"") -> AMG Pantheon | AC80: =IFERROR(VLOOKUP($A80,fund_metadata!$A:$P,16,FALSE),"") -> secondaries
A81: 8 | B81: 45991 | G81: 28.53 | H81: pitchbook | K81: 0.0042 | L81: pitchbook | AB81: =IFERROR(VLOOKUP($A81,fund_metadata!$A:$P,2,FALSE),"") -> AMG Pantheon | AC81: =IFERROR(VLOOKUP($A81,fund_metadata!$A:$P,16,FALSE),"") -> secondaries
A82: 8 | B82: 45961 | G82: 28.41 | H82: pitchbook | K82: -0.0084 | L82: pitchbook | AB82: =IFERROR(VLOOKUP($A82,fund_metadata!$A:$P,2,FALSE),"") -> AMG Pantheon | AC82: =IFERROR(VLOOKUP($A82,fund_metadata!$A:$P,16,FALSE),"") -> secondaries
A83: 8 | B83: 45930 | E83: 5980000000 | F83: pitchbook | G83: 28.65 | H83: pitchbook | K83: 0.0042 | L83: pitchbook | M83: 1 | N83: 6160000000 | O83: pitchbook | P83: 47539435 | Q83: N-CSRS | AB83: =IFERROR(VLOOKUP($A83,fund_metadata!$A:$P,2,FALSE),"") -> AMG Pantheon | AC83: =IFERROR(VLOOKUP($A83,fund_metadata!$A:$P,16,FALSE),"") -> secondaries
A84: 8 | B84: 45900 | G84: 28.53 | H84: pitchbook | K84: 0.0028 | L84: pitchbook | AB84: =IFERROR(VLOOKUP($A84,fund_metadata!$A:$P,2,FALSE),"") -> AMG Pantheon | AC84: =IFERROR(VLOOKUP($A84,fund_metadata!$A:$P,16,FALSE),"") -> secondaries
A85: 8 | B85: 45869 | G85: 28.45 | H85: pitchbook | K85: 0 | L85: pitchbook | AB85: =IFERROR(VLOOKUP($A85,fund_metadata!$A:$P,2,FALSE),"") -> AMG Pantheon | AC85: =IFERROR(VLOOKUP($A85,fund_metadata!$A:$P,16,FALSE),"") -> secondaries
A86: 8 | B86: 45838 | G86: 28.45 | H86: pitchbook | K86: 0.0368 | L86: pitchbook | M86: 1 | AB86: =IFERROR(VLOOKUP($A86,fund_metadata!$A:$P,2,FALSE),"") -> AMG Pantheon | AC86: =IFERROR(VLOOKUP($A86,fund_metadata!$A:$P,16,FALSE),"") -> secondaries
A87: 8 | B87: 45808 | G87: 27.44 | H87: pitchbook | K87: 0.0289 | L87: pitchbook | AB87: =IFERROR(VLOOKUP($A87,fund_metadata!$A:$P,2,FALSE),"") -> AMG Pantheon | AC87: =IFERROR(VLOOKUP($A87,fund_metadata!$A:$P,16,FALSE),"") -> secondaries
A88: 8 | B88: 45777 | G88: 26.67 | H88: pitchbook | K88: 0.0179 | L88: pitchbook | AB88: =IFERROR(VLOOKUP($A88,fund_metadata!$A:$P,2,FALSE),"") -> AMG Pantheon | AC88: =IFERROR(VLOOKUP($A88,fund_metadata!$A:$P,16,FALSE),"") -> secondaries
A89: 8 | B89: 45747 | E89: 4840000000 | F89: pitchbook | G89: 26.2 | H89: pitchbook | K89: -0.0165 | L89: pitchbook | M89: 1 | N89: 5160000000 | O89: pitchbook | P89: 41331380 | Q89: N-CSR | AB89: =IFERROR(VLOOKUP($A89,fund_metadata!$A:$P,2,FALSE),"") -> AMG Pantheon | AC89: =IFERROR(VLOOKUP($A89,fund_metadata!$A:$P,16,FALSE),"") -> secondaries
A90: 8 | B90: 45716 | G90: 26.64 | H90: pitchbook | K90: -0.0316 | L90: pitchbook | AB90: =IFERROR(VLOOKUP($A90,fund_metadata!$A:$P,2,FALSE),"") -> AMG Pantheon | AC90: =IFERROR(VLOOKUP($A90,fund_metadata!$A:$P,16,FALSE),"") -> secondaries
A91: 8 | B91: 45688 | G91: 27.51 | H91: pitchbook | K91: 0.0185 | L91: pitchbook | AB91: =IFERROR(VLOOKUP($A91,fund_metadata!$A:$P,2,FALSE),"") -> AMG Pantheon | AC91: =IFERROR(VLOOKUP($A91,fund_metadata!$A:$P,16,FALSE),"") -> secondaries
A92: 8 | B92: 45657 | G92: 27.01 | H92: pitchbook | K92: 0.0091 | L92: pitchbook | M92: 1 | AB92: =IFERROR(VLOOKUP($A92,fund_metadata!$A:$P,2,FALSE),"") -> AMG Pantheon | AC92: =IFERROR(VLOOKUP($A92,fund_metadata!$A:$P,16,FALSE),"") -> secondaries
A93: 8 | B93: 45626 | G93: 27.01 | H93: pitchbook | K93: 0.0045 | L93: pitchbook | AB93: =IFERROR(VLOOKUP($A93,fund_metadata!$A:$P,2,FALSE),"") -> AMG Pantheon | AC93: =IFERROR(VLOOKUP($A93,fund_metadata!$A:$P,16,FALSE),"") -> secondaries
A94: 8 | B94: 45596 | G94: 26.89 | H94: pitchbook | K94: -0.003 | L94: pitchbook | AB94: =IFERROR(VLOOKUP($A94,fund_metadata!$A:$P,2,FALSE),"") -> AMG Pantheon | AC94: =IFERROR(VLOOKUP($A94,fund_metadata!$A:$P,16,FALSE),"") -> secondaries
A95: 8 | B95: 45565 | E95: 4140000000 | F95: pitchbook | G95: 26.97 | H95: pitchbook | K95: 0.0474 | L95: pitchbook | M95: 1 | N95: 4340000000 | O95: pitchbook | P95: 33303668 | Q95: N-CSRS | AB95: =IFERROR(VLOOKUP($A95,fund_metadata!$A:$P,2,FALSE),"") -> AMG Pantheon | AC95: =IFERROR(VLOOKUP($A95,fund_metadata!$A:$P,16,FALSE),"") -> secondaries
A96: 8 | B96: 45535 | G96: 25.75 | H96: pitchbook | K96: 0.0031 | L96: pitchbook | AB96: =IFERROR(VLOOKUP($A96,fund_metadata!$A:$P,2,FALSE),"") -> AMG Pantheon | AC96: =IFERROR(VLOOKUP($A96,fund_metadata!$A:$P,16,FALSE),"") -> secondaries
A97: 8 | B97: 45504 | G97: 25.67 | H97: pitchbook | K97: 0.0309 | L97: pitchbook | AB97: =IFERROR(VLOOKUP($A97,fund_metadata!$A:$P,2,FALSE),"") -> AMG Pantheon | AC97: =IFERROR(VLOOKUP($A97,fund_metadata!$A:$P,16,FALSE),"") -> secondaries
A98: 8 | B98: 45473 | G98: 24.9 | H98: pitchbook | K98: 0.0172 | L98: pitchbook | M98: 1 | AB98: =IFERROR(VLOOKUP($A98,fund_metadata!$A:$P,2,FALSE),"") -> AMG Pantheon | AC98: =IFERROR(VLOOKUP($A98,fund_metadata!$A:$P,16,FALSE),"") -> secondaries
A99: 8 | B99: 45443 | G99: 24.48 | H99: pitchbook | K99: 0.0221 | L99: pitchbook | AB99: =IFERROR(VLOOKUP($A99,fund_metadata!$A:$P,2,FALSE),"") -> AMG Pantheon | AC99: =IFERROR(VLOOKUP($A99,fund_metadata!$A:$P,16,FALSE),"") -> secondaries
A100: 8 | B100: 45412 | G100: 23.95 | H100: pitchbook | K100: -0.0066 | L100: pitchbook | AB100: =IFERROR(VLOOKUP($A100,fund_metadata!$A:$P,2,FALSE),"") -> AMG Pantheon | AC100: =IFERROR(VLOOKUP($A100,fund_metadata!$A:$P,16,FALSE),"") -> secondaries
...

Sheet fund_metadata
A1: fund_id | B1: fund_name | C1: ticker | D1: cik | E1: share_class_count | F1: sec_name | G1: fund_type | H1: yfinance_link | I1: share_class | J1: direct_statement_name | K1: icapital_name | L1: ms_name | M1: website_link | N1: sgg_holding | O1: class_inception_date | P1: strategy | Q1: management_fee | R1: expense_ratio | S1: incentve_fee | T1: repurchases_liquidity
A2: 1 | B2: Bow River Evergreen PE | C2: EVERX | D2: 1810256 | E2: 2 | F2: Bow River Capital Evergreen Fund | G2: Interval | H2: https://finance.yahoo.com/quote/EVERX/ | I2: Class I | J2: BOW RIVER CAP EVERGREEN FD CL I | M2: https://www.bowriverevergreen.com/ | N2: y | O2: 44196 | P2: private_equity | Q2: 0.0175 | R2: 0.0299
A3: 2 | B3: Carlyle Alpinvest | C3: XCPIX | D3: 1899610 | E3: 4 | F3: Carlyle AlpInvest Private Markets Fund | G3: Tender | H3: https://finance.yahoo.com/quote/XCPIX/ | I3: Class I | J3: Carlyle Alphinvest Prvte Mrkts I | M3: https://www.carlyle.com/capm | N3: y | O3: 45294 | P3: private_equity | Q3: 0.0125 | R3: 0.0324 | S3: 0.1
A4: 3 | B4: Cliffwater | C4: CELFX | D4: 1842754 | E4: 1 | F4: Cliffwater Enhanced Lending Fund | G4: Interval | H4: https://finance.yahoo.com/quote/CELFX/ | I4: Class I | J4: CLIFFWATER ENHANCED LENDING FUND CL I | M4: https://www.cliffwaterfunds.com/celfx | N4: y | O4: 44377 | P4: private_credit | Q4: 0.0095
A5: 4 | B5: Coller Secondaries | D5: 1969180 | E5: 3 | F5: Coller Secondaries Private Equity Opportunities Fund | G5: Tender | I5: Class I | J5: Coller Secondaries Private Equity Opportunities Fund | M5: https://cspef.com/ | N5: y | O5: 45383 | P5: secondaries | Q5: 0.0165
A6: 5 | B6: Stepstone PC Income | C6: CRDEX | D6: 2006100 | E6: 4 | F6: StepStone Private Credit Income Fund | G6: Interval | H6: https://finance.yahoo.com/quote/CRDEX/history/ | I6: Class I | J6: STEPSTONE PRIVATE CREDIT INCOME FD CL I | M6: https://www.stepstonegroup.com/what-we-do/solutions-services/private-wealth-solutions/crdex/ | N6: y | O6: 45446 | P6: private_credit | Q6: 0.0115
A7: 6 | B7: Stepstone Private Markets | C7: XPMIX | D7: 1789470 | E7: 3 | F7: StepStone Private Markets | G7: Tender | H7: https://finance.yahoo.com/quote/XPMIX/ | I7: Class I | J7: STEPSTONE PRIVATE MARKETS I | M7: https://www.stepstonegroup.com/what-we-do/solutions-services/private-wealth-solutions/sprim/ | N7: y | O7: 44105 | P7: secondaries | Q7: 0.014
A8: 7 | B8: Stepstone PV/Growth | C8: XSPIX | D8: 1918642 | E8: 3 | F8: StepStone Private Venture and Growth Fund | G8: Tender | H8: https://finance.yahoo.com/quote/XSPIX/ | I8: Class I | J8: STEPSTONE PRIVATE VENTURE AND GROWTH FD CL I | M8: https://www.stepstonegroup.com/what-we-do/solutions-services/private-wealth-solutions/spring/ | N8: y | O8: 44866 | P8: venture | Q8: 0.015 | T8: 0.025
A9: 8 | B9: AMG Pantheon | C9: XPEIX | D9: 1609211 | E9: 1 | F9: AMG Pantheon Fund, LLC | G9: Tender | I9: Class 3 | K9: AMG PANTHEON FUND CLASS 3 | L9: AMG PANTHEON FUND, LLC ESC | M9: https://www.pantheon.com/private-wealth-overview/amg-pantheon-fund/ | N9: y | O9: 42304 | P9: secondaries | Q9: 0.0125
A10: 9 | B10: FLEX | D10: 2008602 | E10: 4 | F10: Franklin Lexington Private Markets Fund | G10: Tender | I10: Class I | L10: FLEX - CLASS I ESC | M10: https://www.flexpe.com | N10: y | O10: 45646 | P10: secondaries | Q10: 0.0125
A11: 10 | B11: Hamilton Lane | C11: XHLIX | D11: 1803491 | E11: 3 | F11: Hamilton Lane Private Assets Fund | G11: Tender | H11: https://finance.yahoo.com/quote/XHLIX/ | I11: Class I | K11: HAMILTON LANE PVT ASSET FUND CL I | L11: HAMILTON LANE PAF (I) ESC | M11: https://www.hamiltonlane.com/en-us/strategies/evergreen/us-private-wealth/private-assets-fund | N11: y | O11: 44200 | P11: private_equity | Q11: 0.014 | R11: 0.0338 | S11: 0.1 | T11: 0.05
A12: 11 | B12: JPMF | D12: 1940499 | E12: 3 | F12: JPMorgan Private Markets Fund | G12: Tender | I12: Class I | K12: JPMORGAN PRIVATE MARKETS FUND - I | L12: JPMF CLASS I ESC | M12: https://am.jpmorgan.com/us/en/asset-management/adv/products/jpmorgan-private-markets-fund-i-48130f306 | N12: y | O12: 45119 | P12: private_equity | Q12: 0.01

Sheet pitchbook_tri_index
A1: month_end | B1: pitchbook_index
A2: 41820 | B2: 100
A3: 41851 | B3: 99.922618
A4: 41882 | B4: 100.48179
A5: 41912 | B5: 100.70548
A6: 41943 | B6: 101.05813
A7: 41973 | B7: 101.53131
A8: 42004 | B8: 100.99359
A9: 42035 | B9: 101.15965
A10: 42063 | B10: 102.68618
A11: 42094 | B11: 103.68794
A12: 42124 | B12: 104.06627
A13: 42155 | B13: 104.49655
... A139: 45991 | B139: 219.95068
