Workbook
Name _1900_Minority_Interest: [5]summary!#REF!
Name _1995_Asset_Sales: [5]summary!#REF!
Name _1995_Capex: [5]summary!#REF!
Name _1995_Capitalized_Interest: [5]summary!#REF!
Name _1995_Cash_Flow: [5]summary!#REF!
Name _1995_Current_Income_Tax: [5]summary!#REF!
Name _1995_DD_A: [5]summary!#REF!
Name _1995_Deferred_Income_Tax: [5]summary!#REF!
Name _1995_EBIT: [5]summary!#REF!
Name _1995_EBITDAX: [5]summary!#REF!
Name _1995_Exploration_Expense: [5]summary!#REF!
Name _1995_Interest_Expense: [5]summary!#REF!
Name _1995_Net_Income: [5]summary!#REF!
Name _1995_Other_Income: [5]summary!#REF!
Name _1995_Other_Non_Cash_Items: [5]summary!#REF!
Name _1995_Revenue: [5]summary!#REF!
Name _1995_Weighted_Average_Shares_Outstanding: [5]summary!#REF!
Name _1997E_Asset_Sales: [5]summary!#REF!
Name _1997E_Capex: [5]summary!#REF!
Name _1997E_Capitalized_Interest: [5]summary!#REF!
Name _1997E_Cash_Flow: [5]summary!#REF!
Name _1997E_Current_Income_Tax: [5]summary!#REF!
Name _1997E_DD_A: [5]summary!#REF!
Name _1997E_Deferred_Income_Tax: [5]summary!#REF!
Name _1997E_EBIT: [5]summary!#REF!
Name _1997E_EBITDAX: [5]summary!#REF!
Name _1997E_Exploration_Expense: [5]summary!#REF!
Name _1997E_Interest_Expense: [5]summary!#REF!
Name _1997E_Minority_Interest: [5]summary!#REF!
Name _1997E_Net_Income: [5]summary!#REF!
Name _1997E_Other_Income: [5]summary!#REF!
Name _1997E_Other_Non_Cash_Items: [5]summary!#REF!
Name _1997E_Revenue: [5]summary!#REF!
Name _1997E_Weighted_Average_Shares_Outstanding: [5]summary!#REF!
Name _1998E_Asset_Sales: [5]summary!#REF!
Name _1998E_Capex: [5]summary!#REF!
Name _1998E_Capitalized_Interest: [5]summary!#REF!
Name _1998E_Cash_Flow: [5]summary!#REF!
Name _1998E_Current_Income_Tax: [5]summary!#REF!
Name _1998E_DD_A: [5]summary!#REF!
Name _1998E_Deferred_Income_Tax: [5]summary!#REF!
Name _1998E_EBIT: [5]summary!#REF!
Name _1998E_EBITDAX: [5]summary!#REF!
Name _1998E_Exploration_Expense: [5]summary!#REF!
Name _1998E_Interest_Expense: [5]summary!#REF!
Name _1998E_Minority_Interest: [5]summary!#REF!
Name _1998E_Net_Income: [5]summary!#REF!
Name _1998E_Other_Income: [5]summary!#REF!
Name _1998E_Other_Non_Cash_Items: [5]summary!#REF!
Name _1998E_Revenue: [5]summary!#REF!
Name _1998E_Weighted_Average_Shares_Outstanding: [5]summary!#REF!
Name _1999E_Asset_Sales: [5]summary!#REF!
Name _1999E_Capex: [5]summary!#REF!
Name _1999E_Capitalized_Interest: [5]summary!#REF!
Name _1999E_Cash_Flow: [5]summary!#REF!
Name _1999E_Current_Income_Tax: [5]summary!#REF!
Name _1999E_DD_A: [5]summary!#REF!
Name _1999E_Deferred_Income_Tax: [5]summary!#REF!
Name _1999E_EBIT: [5]summary!#REF!
Name _1999E_EBITDAX: [5]summary!#REF!

Sheet fund_performance
A1: fund_id | B1: month_end | C1: redemptions | D1: redemptions_source | E1: distributions | F1: distributions_source | G1: aum | H1: aum_source | I1: sgg_nav | J1: sgg_nav_source | K1: nav | L1: nav_source | M1: nav_per_share | N1: nav_per_share_source | O1: distributions_per_share | P1: distributions_per_share_source | Q1: monthly_return | R1: monthly_return_source | S1: nport_portfolio_count | T1: gav | U1: gav_source | V1: shares_outstanding | W1: shares_outstanding_source | X1: shares_owned | Y1: shares_owned_source | Z1: sgg_purchases | AA1: sgg_purchases_source | AB1: sgg_redemptions | AC1: sgg_redemptions_source | AD1: sgg_distributions | AE1: sgg_distributions_source | AF1: gp_count | AG1: gp_count_source | AH1: fund_name | AI1: strategy
A2: 1 | B2: 43982 | M2: 26.04 | N2: pitchbook | AH2: =IFERROR(VLOOKUP($A2,fund_metadata!$A:$P,2,FALSE),"") -> Bow River Evergreen PE | AI2: =IFERROR(VLOOKUP($A2,fund_metadata!$A:$P,16,FALSE),"") -> private_equity
A3: 1 | B3: 44012 | M3: 28.71 | N3: pitchbook | Q3: 0.1024 | R3: pitchbook | AH3: =IFERROR(VLOOKUP($A3,fund_metadata!$A:$P,2,FALSE),"") -> Bow River Evergreen PE | AI3: =IFERROR(VLOOKUP($A3,fund_metadata!$A:$P,16,FALSE),"") -> private_equity
A4: 1 | B4: 44043 | M4: 28.78 | N4: pitchbook | Q4: 0.0026 | R4: pitchbook | AH4: =IFERROR(VLOOKUP($A4,fund_metadata!$A:$P,2,FALSE),"") -> Bow River Evergreen PE | AI4: =IFERROR(VLOOKUP($A4,fund_metadata!$A:$P,16,FALSE),"") -> private_equity
A5: 1 | B5: 44074 | M5: 28.83 | N5: pitchbook | Q5: 0.0016 | R5: pitchbook | AH5: =IFERROR(VLOOKUP($A5,fund_metadata!$A:$P,2,FALSE),"") -> Bow River Evergreen PE | AI5: =IFERROR(VLOOKUP($A5,fund_metadata!$A:$P,16,FALSE),"") -> private_equity
A6: 1 | B6: 44104 | M6: 29.26 | N6: pitchbook | Q6: 0.0149 | R6: pitchbook | AH6: =IFERROR(VLOOKUP($A6,fund_metadata!$A:$P,2,FALSE),"") -> Bow River Evergreen PE | AI6: =IFERROR(VLOOKUP($A6,fund_metadata!$A:$P,16,FALSE),"") -> private_equity
A7: 1 | B7: 44135 | M7: 29.26 | N7: pitchbook | Q7: 0.0001 | R7: pitchbook | AH7: =IFERROR(VLOOKUP($A7,fund_metadata!$A:$P,2,FALSE),"") -> Bow River Evergreen PE | AI7: =IFERROR(VLOOKUP($A7,fund_metadata!$A:$P,16,FALSE),"") -> private_equity
A8: 1 | B8: 44165 | M8: 29.6 | N8: pitchbook | Q8: 0.0118 | R8: pitchbook | AH8: =IFERROR(VLOOKUP($A8,fund_metadata!$A:$P,2,FALSE),"") -> Bow River Evergreen PE | AI8: =IFERROR(VLOOKUP($A8,fund_metadata!$A:$P,16,FALSE),"") -> private_equity
A9: 1 | B9: 44196 | M9: 29.58 | N9: pitchbook | Q9: -0.0008 | R9: pitchbook | AH9: =IFERROR(VLOOKUP($A9,fund_metadata!$A:$P,2,FALSE),"") -> Bow River Evergreen PE | AI9: =IFERROR(VLOOKUP($A9,fund_metadata!$A:$P,16,FALSE),"") -> private_equity
A10: 1 | B10: 44227 | M10: 30.39 | N10: pitchbook | Q10: 0.0273 | R10: pitchbook | AH10: =IFERROR(VLOOKUP($A10,fund_metadata!$A:$P,2,FALSE),"") -> Bow River Evergreen PE | AI10: =IFERROR(VLOOKUP($A10,fund_metadata!$A:$P,16,FALSE),"") -> private_equity
A11: 1 | B11: 44255 | M11: 31.19 | N11: pitchbook | Q11: 0.0264 | R11: pitchbook | AH11: =IFERROR(VLOOKUP($A11,fund_metadata!$A:$P,2,FALSE),"") -> Bow River Evergreen PE | AI11: =IFERROR(VLOOKUP($A11,fund_metadata!$A:$P,16,FALSE),"") -> private_equity
A12: 1 | B12: 44286 | M12: 31.77 | N12: pitchbook | Q12: 0.0186 | R12: pitchbook | S12: 32 | V12: 2869318 | W12: N-CSR | AH12: =IFERROR(VLOOKUP($A12,fund_metadata!$A:$P,2,FALSE),"") -> Bow River Evergreen PE | AI12: =IFERROR(VLOOKUP($A12,fund_metadata!$A:$P,16,FALSE),"") -> private_equity
A13: 1 | B13: 44316 | M13: 31.79 | N13: pitchbook | Q13: 0.0007 | R13: pitchbook | AH13: =IFERROR(VLOOKUP($A13,fund_metadata!$A:$P,2,FALSE),"") -> Bow River Evergreen PE | AI13: =IFERROR(VLOOKUP($A13,fund_metadata!$A:$P,16,FALSE),"") -> private_equity
A14: 1 | B14: 44347 | M14: 33.04 | N14: pitchbook | Q14: 0.0394 | R14: pitchbook | AH14: =IFERROR(VLOOKUP($A14,fund_metadata!$A:$P,2,FALSE),"") -> Bow River Evergreen PE | AI14: =IFERROR(VLOOKUP($A14,fund_metadata!$A:$P,16,FALSE),"") -> private_equity
A15: 1 | B15: 44377 | K15: 127850000 | L15: pitchbook | M15: 33.84 | N15: pitchbook | Q15: 0.0242 | R15: pitchbook | S15: 40 | AH15: =IFERROR(VLOOKUP($A15,fund_metadata!$A:$P,2,FALSE),"") -> Bow River Evergreen PE | AI15: =IFERROR(VLOOKUP($A15,fund_metadata!$A:$P,16,FALSE),"") -> private_equity
A16: 1 | B16: 44408 | K16: 131660000 | L16: pitchbook | M16: 34.52 | N16: pitchbook | Q16: 0.02 | R16: pitchbook | AH16: =IFERROR(VLOOKUP($A16,fund_metadata!$A:$P,2,FALSE),"") -> Bow River Evergreen PE | AI16: =IFERROR(VLOOKUP($A16,fund_metadata!$A:$P,16,FALSE),"") -> private_equity
A17: 1 | B17: 44439 | K17: 141200000 | L17: pitchbook | M17: 36.01 | N17: pitchbook | Q17: 0.0432 | R17: pitchbook | AH17: =IFERROR(VLOOKUP($A17,fund_metadata!$A:$P,2,FALSE),"") -> Bow River Evergreen PE | AI17: =IFERROR(VLOOKUP($A17,fund_metadata!$A:$P,16,FALSE),"") -> private_equity
A18: 1 | B18: 44469 | K18: 150110000 | L18: pitchbook | M18: 36.75 | N18: pitchbook | Q18: 0.0204 | R18: pitchbook | S18: 46 | V18: 4085205 | W18: N-CSRS | AH18: =IFERROR(VLOOKUP($A18,fund_metadata!$A:$P,2,FALSE),"") -> Bow River Evergreen PE | AI18: =IFERROR(VLOOKUP($A18,fund_metadata!$A:$P,16,FALSE),"") -> private_equity
A19: 1 | B19: 44500 | K19: 152780000 | L19: pitchbook | M19: 36.76 | N19: pitchbook | Q19: 0.0004 | R19: pitchbook | AH19: =IFERROR(VLOOKUP($A19,fund_metadata!$A:$P,2,FALSE),"") -> Bow River Evergreen PE | AI19: =IFERROR(VLOOKUP($A19,fund_metadata!$A:$P,16,FALSE),"") -> private_equity
A20: 1 | B20: 44530 | K20: 172670000 | L20: pitchbook | M20: 38.41 | N20: pitchbook | Q20: 0.0449 | R20: pitchbook | AH20: =IFERROR(VLOOKUP($A20,fund_metadata!$A:$P,2,FALSE),"") -> Bow River Evergreen PE | AI20: =IFERROR(VLOOKUP($A20,fund_metadata!$A:$P,16,FALSE),"") -> private_equity
A21: 1 | B21: 44561 | K21: 181180000 | L21: pitchbook | M21: 38.38 | N21: pitchbook | Q21: 0.0063 | R21: pitchbook | S21: 53 | AH21: =IFERROR(VLOOKUP($A21,fund_metadata!$A:$P,2,FALSE),"") -> Bow River Evergreen PE | AI21: =IFERROR(VLOOKUP($A21,fund_metadata!$A:$P,16,FALSE),"") -> private_equity
A22: 1 | B22: 44592 | K22: 191620000 | L22: pitchbook | M22: 38.01 | N22: pitchbook | Q22: -0.0097 | R22: pitchbook | AH22: =IFERROR(VLOOKUP($A22,fund_metadata!$A:$P,2,FALSE),"") -> Bow River Evergreen PE | AI22: =IFERROR(VLOOKUP($A22,fund_metadata!$A:$P,16,FALSE),"") -> private_equity
A23: 1 | B23: 44620 | K23: 206170000 | L23: pitchbook | M23: 38.6 | N23: pitchbook | Q23: 0.0157 | R23: pitchbook | AH23: =IFERROR(VLOOKUP($A23,fund_metadata!$A:$P,2,FALSE),"") -> Bow River Evergreen PE | AI23: =IFERROR(VLOOKUP($A23,fund_metadata!$A:$P,16,FALSE),"") -> private_equity
A24: 1 | B24: 44651 | K24: 217280000 | L24: pitchbook | M24: 39.5 | N24: pitchbook | Q24: 0.0232 | R24: pitchbook | S24: 64 | T24: 230020000 | U24: pitchbook | V24: 5341595 | W24: N-CSR | AH24: =IFERROR(VLOOKUP($A24,fund_metadata!$A:$P,2,FALSE),"") -> Bow River Evergreen PE | AI24: =IFERROR(VLOOKUP($A24,fund_metadata!$A:$P,16,FALSE),"") -> private_equity
A25: 1 | B25: 44681 | K25: 227980000 | L25: pitchbook | M25: 39.68 | N25: pitchbook | Q25: 0.0045 | R25: pitchbook | AH25: =IFERROR(VLOOKUP($A25,fund_metadata!$A:$P,2,FALSE),"") -> Bow River Evergreen PE | AI25: =IFERROR(VLOOKUP($A25,fund_metadata!$A:$P,16,FALSE),"") -> private_equity
A26: 1 | B26: 44712 | K26: 238290000 | L26: pitchbook | M26: 40.13 | N26: pitchbook | Q26: 0.0114 | R26: pitchbook | AH26: =IFERROR(VLOOKUP($A26,fund_metadata!$A:$P,2,FALSE),"") -> Bow River Evergreen PE | AI26: =IFERROR(VLOOKUP($A26,fund_metadata!$A:$P,16,FALSE),"") -> private_equity
A27: 1 | B27: 44742 | K27: 247830000 | L27: pitchbook | M27: 39.92 | N27: pitchbook | Q27: -0.0053 | R27: pitchbook | S27: 79 | AH27: =IFERROR(VLOOKUP($A27,fund_metadata!$A:$P,2,FALSE),"") -> Bow River Evergreen PE | AI27: =IFERROR(VLOOKUP($A27,fund_metadata!$A:$P,16,FALSE),"") -> private_equity
A28: 1 | B28: 44773 | K28: 257890000 | L28: pitchbook | M28: 39.76 | N28: pitchbook | Q28: -0.0039 | R28: pitchbook | AH28: =IFERROR(VLOOKUP($A28,fund_metadata!$A:$P,2,FALSE),"") -> Bow River Evergreen PE | AI28: =IFERROR(VLOOKUP($A28,fund_metadata!$A:$P,16,FALSE),"") -> private_equity
A29: 1 | B29: 44804 | K29: 269150000 | L29: pitchbook | M29: 39.94 | N29: pitchbook | Q29: 0.0045 | R29: pitchbook | AH29: =IFERROR(VLOOKUP($A29,fund_metadata!$A:$P,2,FALSE),"") -> Bow River Evergreen PE | AI29: =IFERROR(VLOOKUP($A29,fund_metadata!$A:$P,16,FALSE),"") -> private_equity
A30: 1 | B30: 44834 | K30: 279610000 | L30: pitchbook | M30: 39.87 | N30: pitchbook | Q30: -0.0018 | R30: pitchbook | S30: 88 | T30: 292180000 | U30: pitchbook | V30: 6459606 | W30: N-CSRS | AH30: =IFERROR(VLOOKUP($A30,fund_metadata!$A:$P,2,FALSE),"") -> Bow River Evergreen PE | AI30: =IFERROR(VLOOKUP($A30,fund_metadata!$A:$P,16,FALSE),"") -> private_equity
A31: 1 | B31: 44865 | K31: 286020000 | L31: pitchbook | M31: 39.75 | N31: pitchbook | Q31: -0.003 | R31: pitchbook | AH31: =IFERROR(VLOOKUP($A31,fund_metadata!$A:$P,2,FALSE),"") -> Bow River Evergreen PE | AI31: =IFERROR(VLOOKUP($A31,fund_metadata!$A:$P,16,FALSE),"") -> private_equity
A32: 1 | B32: 44895 | K32: 296020000 | L32: pitchbook | M32: 40.18 | N32: pitchbook | Q32: 0.0107 | R32: pitchbook | AH32: =IFERROR(VLOOKUP($A32,fund_metadata!$A:$P,2,FALSE),"") -> Bow River Evergreen PE | AI32: =IFERROR(VLOOKUP($A32,fund_metadata!$A:$P,16,FALSE),"") -> private_equity
A33: 1 | B33: 44926 | K33: 299140000 | L33: pitchbook | M33: 39.39 | N33: pitchbook | Q33: 0.0081 | R33: pitchbook | S33: 96 | AH33: =IFERROR(VLOOKUP($A33,fund_metadata!$A:$P,2,FALSE),"") -> Bow River Evergreen PE | AI33: =IFERROR(VLOOKUP($A33,fund_metadata!$A:$P,16,FALSE),"") -> private_equity
A34: 1 | B34: 44957 | K34: 314370000 | L34: pitchbook | M34: 39.39 | N34: pitchbook | Q34: 0.0001 | R34: pitchbook | AH34: =IFERROR(VLOOKUP($A34,fund_metadata!$A:$P,2,FALSE),"") -> Bow River Evergreen PE | AI34: =IFERROR(VLOOKUP($A34,fund_metadata!$A:$P,16,FALSE),"") -> private_equity
A35: 1 | B35: 44985 | K35: 325700000 | L35: pitchbook | M35: 39.94 | N35: pitchbook | Q35: 0.0141 | R35: pitchbook | AH35: =IFERROR(VLOOKUP($A35,fund_metadata!$A:$P,2,FALSE),"") -> Bow River Evergreen PE | AI35: =IFERROR(VLOOKUP($A35,fund_metadata!$A:$P,16,FALSE),"") -> private_equity
A36: 1 | B36: 45016 | K36: 341380000 | L36: pitchbook | M36: 40.09 | N36: pitchbook | Q36: 0.0038 | R36: pitchbook | S36: 98 | T36: 353810000 | U36: pitchbook | AH36: =IFERROR(VLOOKUP($A36,fund_metadata!$A:$P,2,FALSE),"") -> Bow River Evergreen PE | AI36: =IFERROR(VLOOKUP($A36,fund_metadata!$A:$P,16,FALSE),"") -> private_equity
A37: 1 | B37: 45046 | K37: 352740000 | L37: pitchbook | M37: 40.41 | N37: pitchbook | Q37: 0.0078 | R37: pitchbook | AH37: =IFERROR(VLOOKUP($A37,fund_metadata!$A:$P,2,FALSE),"") -> Bow River Evergreen PE | AI37: =IFERROR(VLOOKUP($A37,fund_metadata!$A:$P,16,FALSE),"") -> private_equity
A38: 1 | B38: 45077 | K38: 357990000 | L38: pitchbook | M38: 40.41 | N38: pitchbook | Q38: 0.0002 | R38: pitchbook | AH38: =IFERROR(VLOOKUP($A38,fund_metadata!$A:$P,2,FALSE),"") -> Bow River Evergreen PE | AI38: =IFERROR(VLOOKUP($A38,fund_metadata!$A:$P,16,FALSE),"") -> private_equity
A39: 1 | B39: 45107 | K39: 369270000 | L39: pitchbook | M39: 40.69 | N39: pitchbook | Q39: 0.0068 | R39: pitchbook | S39: 98 | AH39: =IFERROR(VLOOKUP($A39,fund_metadata!$A:$P,2,FALSE),"") -> Bow River Evergreen PE | AI39: =IFERROR(VLOOKUP($A39,fund_metadata!$A:$P,16,FALSE),"") -> private_equity
A40: 1 | B40: 45138 | K40: 380550000 | L40: pitchbook | M40: 41.15 | N40: pitchbook | Q40: 0.0113 | R40: pitchbook | AH40: =IFERROR(VLOOKUP($A40,fund_metadata!$A:$P,2,FALSE),"") -> Bow River Evergreen PE | AI40: =IFERROR(VLOOKUP($A40,fund_metadata!$A:$P,16,FALSE),"") -> private_equity
A41: 1 | B41: 45169 | K41: 395660000 | L41: pitchbook | M41: 42 | N41: pitchbook | Q41: 0.0206 | R41: pitchbook | AH41: =IFERROR(VLOOKUP($A41,fund_metadata!$A:$P,2,FALSE),"") -> Bow River Evergreen PE | AI41: =IFERROR(VLOOKUP($A41,fund_metadata!$A:$P,16,FALSE),"") -> private_equity
A42: 1 | B42: 45199 | K42: 400100000 | L42: pitchbook | M42: 41.9 | N42: pitchbook | Q42: -0.0023 | R42: pitchbook | S42: 105 | T42: 412100000 | U42: pitchbook | V42: 8965808 | W42: N-CSRS | AH42: =IFERROR(VLOOKUP($A42,fund_metadata!$A:$P,2,FALSE),"") -> Bow River Evergreen PE | AI42: =IFERROR(VLOOKUP($A42,fund_metadata!$A:$P,16,FALSE),"") -> private_equity
A43: 1 | B43: 45230 | K43: 427670000 | L43: pitchbook | M43: 43.45 | N43: pitchbook | Q43: 0.0371 | R43: pitchbook | AH43: =IFERROR(VLOOKUP($A43,fund_metadata!$A:$P,2,FALSE),"") -> Bow River Evergreen PE | AI43: =IFERROR(VLOOKUP($A43,fund_metadata!$A:$P,16,FALSE),"") -> private_equity
A44: 1 | B44: 45260 | K44: 438230000 | L44: pitchbook | M44: 43.98 | N44: pitchbook | Q44: 0.012 | R44: pitchbook | AH44: =IFERROR(VLOOKUP($A44,fund_metadata!$A:$P,2,FALSE),"") -> Bow River Evergreen PE | AI44: =IFERROR(VLOOKUP($A44,fund_metadata!$A:$P,16,FALSE),"") -> private_equity
A45: 1 | B45: 45291 | K45: 446350000 | L45: pitchbook | M45: 43.37 | N45: pitchbook | Q45: 0.0018 | R45: pitchbook | S45: 106 | AH45: =IFERROR(VLOOKUP($A45,fund_metadata!$A:$P,2,FALSE),"") -> Bow River Evergreen PE | AI45: =IFERROR(VLOOKUP($A45,fund_metadata!$A:$P,16,FALSE),"") -> private_equity
A46: 1 | B46: 45322 | K46: 459740000 | L46: pitchbook | M46: 43.36 | N46: pitchbook | Q46: -0.0002 | R46: pitchbook | AH46: =IFERROR(VLOOKUP($A46,fund_metadata!$A:$P,2,FALSE),"") -> Bow River Evergreen PE | AI46: =IFERROR(VLOOKUP($A46,fund_metadata!$A:$P,16,FALSE),"") -> private_equity
A47: 1 | B47: 45351 | K47: 476530000 | L47: pitchbook | M47: 43.93 | N47: pitchbook | Q47: 0.0131 | R47: pitchbook | AH47: =IFERROR(VLOOKUP($A47,fund_metadata!$A:$P,2,FALSE),"") -> Bow River Evergreen PE | AI47: =IFERROR(VLOOKUP($A47,fund_metadata!$A:$P,16,FALSE),"") -> private_equity
A48: 1 | B48: 45382 | K48: 486790000 | L48: pitchbook | M48: 44.29 | N48: pitchbook | Q48: 0.0082 | R48: pitchbook | S48: 112 | T48: 519920000 | U48: pitchbook | V48: 10327322 | W48: N-CSR | AH48: =IFERROR(VLOOKUP($A48,fund_metadata!$A:$P,2,FALSE),"") -> Bow River Evergreen PE | AI48: =IFERROR(VLOOKUP($A48,fund_metadata!$A:$P,16,FALSE),"") -> private_equity
A49: 1 | B49: 45412 | K49: 509290000 | L49: pitchbook | M49: 44.88 | N49: pitchbook | Q49: 0.0134 | R49: pitchbook | AH49: =IFERROR(VLOOKUP($A49,fund_metadata!$A:$P,2,FALSE),"") -> Bow River Evergreen PE | AI49: =IFERROR(VLOOKUP($A49,fund_metadata!$A:$P,16,FALSE),"") -> private_equity
A50: 1 | B50: 45443 | K50: 530130000 | L50: pitchbook | M50: 45.83 | N50: pitchbook | Q50: 0.0212 | R50: pitchbook | AH50: =IFERROR(VLOOKUP($A50,fund_metadata!$A:$P,2,FALSE),"") -> Bow River Evergreen PE | AI50: =IFERROR(VLOOKUP($A50,fund_metadata!$A:$P,16,FALSE),"") -> private_equity
A51: 1 | B51: 45473 | K51: 552750000 | L51: pitchbook | M51: 45.85 | N51: pitchbook | O51: 0 | P51: yfinance | Q51: 0.0004 | R51: pitchbook | S51: 121 | AH51: =IFERROR(VLOOKUP($A51,fund_metadata!$A:$P,2,FALSE),"") -> Bow River Evergreen PE | AI51: =IFERROR(VLOOKUP($A51,fund_metadata!$A:$P,16,FALSE),"") -> private_equity
A52: 1 | B52: 45504 | K52: 565090000 | L52: pitchbook | M52: 45.9 | N52: pitchbook | O52: 0 | P52: yfinance | Q52: 0.0011 | R52: pitchbook | AH52: =IFERROR(VLOOKUP($A52,fund_metadata!$A:$P,2,FALSE),"") -> Bow River Evergreen PE | AI52: =IFERROR(VLOOKUP($A52,fund_metadata!$A:$P,16,FALSE),"") -> private_equity
A53: 1 | B53: 45535 | K53: 600190000 | L53: pitchbook | M53: 47.24 | N53: pitchbook | O53: 0 | P53: yfinance | Q53: 0.029 | R53: pitchbook | AH53: =IFERROR(VLOOKUP($A53,fund_metadata!$A:$P,2,FALSE),"") -> Bow River Evergreen PE | AI53: =IFERROR(VLOOKUP($A53,fund_metadata!$A:$P,16,FALSE),"") -> private_equity
A54: 1 | B54: 45565 | K54: 617640000 | L54: pitchbook | M54: 47.8 | N54: pitchbook | O54: 0 | P54: yfinance | Q54: 0.0119 | R54: pitchbook | S54: 131 | T54: 632440000 | U54: pitchbook | V54: 12219603 | W54: N-CSRS | AH54: =IFERROR(VLOOKUP($A54,fund_metadata!$A:$P,2,FALSE),"") -> Bow River Evergreen PE | AI54: =IFERROR(VLOOKUP($A54,fund_metadata!$A:$P,16,FALSE),"") -> private_equity
A55: 1 | B55: 45596 | K55: 633880000 | L55: pitchbook | M55: 47.94 | N55: pitchbook | O55: 0 | P55: yfinance | Q55: 0.0028 | R55: pitchbook | AH55: =IFERROR(VLOOKUP($A55,fund_metadata!$A:$P,2,FALSE),"") -> Bow River Evergreen PE | AI55: =IFERROR(VLOOKUP($A55,fund_metadata!$A:$P,16,FALSE),"") -> private_equity
A56: 1 | B56: 45626 | K56: 658210000 | L56: pitchbook | M56: 48.48 | N56: pitchbook | O56: 0 | P56: yfinance | Q56: 0.0115 | R56: pitchbook | AH56: =IFERROR(VLOOKUP($A56,fund_metadata!$A:$P,2,FALSE),"") -> Bow River Evergreen PE | AI56: =IFERROR(VLOOKUP($A56,fund_metadata!$A:$P,16,FALSE),"") -> private_equity
A57: 1 | B57: 45657 | K57: 669420000 | L57: pitchbook | M57: 47.54 | N57: pitchbook | O57: 1.137 | P57: yfinance | Q57: 0.004 | R57: pitchbook | S57: 142 | AH57: =IFERROR(VLOOKUP($A57,fund_metadata!$A:$P,2,FALSE),"") -> Bow River Evergreen PE | AI57: =IFERROR(VLOOKUP($A57,fund_metadata!$A:$P,16,FALSE),"") -> private_equity
A58: 1 | B58: 45688 | K58: 701580000 | L58: pitchbook | M58: 47.77 | N58: pitchbook | O58: 0 | P58: yfinance | Q58: 0.005 | R58: pitchbook | AH58: =IFERROR(VLOOKUP($A58,fund_metadata!$A:$P,2,FALSE),"") -> Bow River Evergreen PE | AI58: =IFERROR(VLOOKUP($A58,fund_metadata!$A:$P,16,FALSE),"") -> private_equity
A59: 1 | B59: 45716 | K59: 735550000 | L59: pitchbook | M59: 48.8 | N59: pitchbook | O59: 0 | P59: yfinance | Q59: 0.0215 | R59: pitchbook | AH59: =IFERROR(VLOOKUP($A59,fund_metadata!$A:$P,2,FALSE),"") -> Bow River Evergreen PE | AI59: =IFERROR(VLOOKUP($A59,fund_metadata!$A:$P,16,FALSE),"") -> private_equity
A60: 1 | B60: 45747 | K60: 774220000 | L60: pitchbook | M60: 49.69 | N60: pitchbook | O60: 0 | P60: yfinance | Q60: 0.0182 | R60: pitchbook | S60: 147 | T60: 817800000 | U60: pitchbook | V60: 14550293 | W60: N-CSR | AH60: =IFERROR(VLOOKUP($A60,fund_metadata!$A:$P,2,FALSE),"") -> Bow River Evergreen PE | AI60: =IFERROR(VLOOKUP($A60,fund_metadata!$A:$P,16,FALSE),"") -> private_equity
A61: 1 | B61: 45777 | K61: 807000000 | L61: pitchbook | M61: 50.09 | N61: pitchbook | O61: 0 | P61: yfinance | Q61: 0.0081 | R61: pitchbook | AH61: =IFERROR(VLOOKUP($A61,fund_metadata!$A:$P,2,FALSE),"") -> Bow River Evergreen PE | AI61: =IFERROR(VLOOKUP($A61,fund_metadata!$A:$P,16,FALSE),"") -> private_equity
A62: 1 | B62: 45808 | K62: 826540000 | L62: pitchbook | M62: 50.8 | N62: pitchbook | O62: 0 | P62: yfinance | Q62: 0.0142 | R62: pitchbook | AH62: =IFERROR(VLOOKUP($A62,fund_metadata!$A:$P,2,FALSE),"") -> Bow River Evergreen PE | AI62: =IFERROR(VLOOKUP($A62,fund_metadata!$A:$P,16,FALSE),"") -> private_equity
A63: 1 | B63: 45838 | K63: 849670000 | L63: pitchbook | M63: 50.82 | N63: pitchbook | O63: 0 | P63: yfinance | Q63: 0.0004 | R63: pitchbook | S63: 157 | AH63: =IFERROR(VLOOKUP($A63,fund_metadata!$A:$P,2,FALSE),"") -> Bow River Evergreen PE | AI63: =IFERROR(VLOOKUP($A63,fund_metadata!$A:$P,16,FALSE),"") -> private_equity
A64: 1 | B64: 45869 | K64: 894140000 | L64: pitchbook | M64: 50.72 | N64: pitchbook | Q64: -0.002 | R64: pitchbook | AH64: =IFERROR(VLOOKUP($A64,fund_metadata!$A:$P,2,FALSE),"") -> Bow River Evergreen PE | AI64: =IFERROR(VLOOKUP($A64,fund_metadata!$A:$P,16,FALSE),"") -> private_equity
A65: 1 | B65: 45900 | K65: 942530000 | L65: pitchbook | M65: 51.69 | N65: pitchbook | Q65: 0.0191 | R65: pitchbook | AH65: =IFERROR(VLOOKUP($A65,fund_metadata!$A:$P,2,FALSE),"") -> Bow River Evergreen PE | AI65: =IFERROR(VLOOKUP($A65,fund_metadata!$A:$P,16,FALSE),"") -> private_equity
A66: 1 | B66: 45930 | K66: 1000000000 | L66: pitchbook | M66: 52.03 | N66: pitchbook | Q66: 0.0066 | R66: pitchbook | S66: 176 | T66: 1040000000 | U66: pitchbook | V66: 18405421 | W66: N-CSRS | AH66: =IFERROR(VLOOKUP($A66,fund_metadata!$A:$P,2,FALSE),"") -> Bow River Evergreen PE | AI66: =IFERROR(VLOOKUP($A66,fund_metadata!$A:$P,16,FALSE),"") -> private_equity
A67: 1 | B67: 45961 | K67: 1050000000 | L67: pitchbook | M67: 52.68 | N67: pitchbook | Q67: 0.0125 | R67: pitchbook | AH67: =IFERROR(VLOOKUP($A67,fund_metadata!$A:$P,2,FALSE),"") -> Bow River Evergreen PE | AI67: =IFERROR(VLOOKUP($A67,fund_metadata!$A:$P,16,FALSE),"") -> private_equity
A68: 1 | B68: 45991 | K68: 1090000000 | L68: pitchbook | M68: 54.36 | N68: pitchbook | Q68: 0.0319 | R68: pitchbook | AH68: =IFERROR(VLOOKUP($A68,fund_metadata!$A:$P,2,FALSE),"") -> Bow River Evergreen PE | AI68: =IFERROR(VLOOKUP($A68,fund_metadata!$A:$P,16,FALSE),"") -> private_equity
A69: 1 | B69: 46022 | K69: 1120000000 | L69: pitchbook | M69: 53.75 | N69: pitchbook | Q69: -0.0113 | R69: pitchbook | S69: 185 | AH69: =IFERROR(VLOOKUP($A69,fund_metadata!$A:$P,2,FALSE),"") -> Bow River Evergreen PE | AI69: =IFERROR(VLOOKUP($A69,fund_metadata!$A:$P,16,FALSE),"") -> private_equity
A70: 1 | B70: 46053 | I70: 5059902.1 | J70: direct fund statement | K70: 1160000000 | L70: pitchbook | M70: 54.39 | N70: pitchbook | Q70: 0.012 | R70: pitchbook | X70: 93030.179 | Y70: direct fund statement | Z70: 5000000 | AA70: direct fund statement | AB70: 0 | AC70: direct fund statement | AD70: 0 | AE70: direct fund statement | AH70: =IFERROR(VLOOKUP($A70,fund_metadata!$A:$P,2,FALSE),"") -> Bow River Evergreen PE | AI70: =IFERROR(VLOOKUP($A70,fund_metadata!$A:$P,16,FALSE),"") -> private_equity
A71: 1 | B71: 46081 | I71: 5094704.7 | J71: direct fund statement | K71: 1190000000 | L71: pitchbook | M71: 54.76 | N71: pitchbook | Q71: 0.0069 | R71: pitchbook | X71: 93030.179 | Y71: direct fund statement | Z71: 0 | AA71: direct fund statement | AB71: 0 | AC71: direct fund statement | AD71: 0 | AE71: direct fund statement | AH71: =IFERROR(VLOOKUP($A71,fund_metadata!$A:$P,2,FALSE),"") -> Bow River Evergreen PE | AI71: =IFERROR(VLOOKUP($A71,fund_metadata!$A:$P,16,FALSE),"") -> private_equity
A72: 1 | B72: 46112 | I72: 5114594.6 | J72: direct fund statement | K72: 1220000000 | L72: pitchbook | M72: 54.98 | N72: pitchbook | Q72: 0.0039 | R72: pitchbook | S72: 198 | X72: 93030.179 | Y72: direct fund statement | Z72: 0 | AA72: direct fund statement | AB72: 0 | AC72: direct fund statement | AD72: 0 | AE72: direct fund statement | AH72: =IFERROR(VLOOKUP($A72,fund_metadata!$A:$P,2,FALSE),"") -> Bow River Evergreen PE | AI72: =IFERROR(VLOOKUP($A72,fund_metadata!$A:$P,16,FALSE),"") -> private_equity
A73: 1 | B73: 46142 | I73: 5132009.8 | J73: black diamond | K73: 1240000000 | L73: pitchbook | M73: 55.17 | N73: pitchbook | Q73: 0.0034 | R73: pitchbook | AH73: =IFERROR(VLOOKUP($A73,fund_metadata!$A:$P,2,FALSE),"") -> Bow River Evergreen PE | AI73: =IFERROR(VLOOKUP($A73,fund_metadata!$A:$P,16,FALSE),"") -> private_equity
A74: 1 | B74: 46173 | M74: 55.56 | N74: pitchbook | AH74: =IFERROR(VLOOKUP($A74,fund_metadata!$A:$P,2,FALSE),"") -> Bow River Evergreen PE | AI74: =IFERROR(VLOOKUP($A74,fund_metadata!$A:$P,16,FALSE),"") -> private_equity
A75: 2 | B75: 44926 | M75: 10 | N75: pitchbook | AH75: =IFERROR(VLOOKUP($A75,fund_metadata!$A:$P,2,FALSE),"") -> Carlyle Alpinvest | AI75: =IFERROR(VLOOKUP($A75,fund_metadata!$A:$P,16,FALSE),"") -> private_equity
A76: 2 | B76: 44957 | K76: 185800000 | L76: pitchbook | M76: 10.08 | N76: pitchbook | Q76: 0.008 | R76: pitchbook | AH76: =IFERROR(VLOOKUP($A76,fund_metadata!$A:$P,2,FALSE),"") -> Carlyle Alpinvest | AI76: =IFERROR(VLOOKUP($A76,fund_metadata!$A:$P,16,FALSE),"") -> private_equity
A77: 2 | B77: 44985 | K77: 189310000 | L77: pitchbook | M77: 10.27 | N77: pitchbook | Q77: 0.0188 | R77: pitchbook | AH77: =IFERROR(VLOOKUP($A77,fund_metadata!$A:$P,2,FALSE),"") -> Carlyle Alpinvest | AI77: =IFERROR(VLOOKUP($A77,fund_metadata!$A:$P,16,FALSE),"") -> private_equity
A78: 2 | B78: 45016 | K78: 190250000 | L78: pitchbook | M78: 10.32 | N78: pitchbook | Q78: 0.0049 | R78: pitchbook | S78: 134 | V78: 18427054 | W78: N-CSR | AH78: =IFERROR(VLOOKUP($A78,fund_metadata!$A:$P,2,FALSE),"") -> Carlyle Alpinvest | AI78: =IFERROR(VLOOKUP($A78,fund_metadata!$A:$P,16,FALSE),"") -> private_equity
A79: 2 | B79: 45046 | K79: 190530000 | L79: pitchbook | M79: 10.34 | N79: pitchbook | Q79: 0.0019 | R79: pitchbook | AH79: =IFERROR(VLOOKUP($A79,fund_metadata!$A:$P,2,FALSE),"") -> Carlyle Alpinvest | AI79: =IFERROR(VLOOKUP($A79,fund_metadata!$A:$P,16,FALSE),"") -> private_equity
A80: 2 | B80: 45077 | K80: 198720000 | L80: pitchbook | M80: 10.74 | N80: pitchbook | Q80: 0.0387 | R80: pitchbook | AH80: =IFERROR(VLOOKUP($A80,fund_metadata!$A:$P,2,FALSE),"") -> Carlyle Alpinvest | AI80: =IFERROR(VLOOKUP($A80,fund_metadata!$A:$P,16,FALSE),"") -> private_equity
A81: 2 | B81: 45107 | K81: 203490000 | L81: pitchbook | M81: 10.99 | N81: pitchbook | Q81: 0.0233 | R81: pitchbook | S81: 136 | AH81: =IFERROR(VLOOKUP($A81,fund_metadata!$A:$P,2,FALSE),"") -> Carlyle Alpinvest | AI81: =IFERROR(VLOOKUP($A81,fund_metadata!$A:$P,16,FALSE),"") -> private_equity
A82: 2 | B82: 45138 | K82: 208950000 | L82: pitchbook | M82: 11.19 | N82: pitchbook | O82: 0 | P82: yfinance | Q82: 0.0182 | R82: pitchbook | AH82: =IFERROR(VLOOKUP($A82,fund_metadata!$A:$P,2,FALSE),"") -> Carlyle Alpinvest | AI82: =IFERROR(VLOOKUP($A82,fund_metadata!$A:$P,16,FALSE),"") -> private_equity
A83: 2 | B83: 45169 | K83: 224020000 | L83: pitchbook | M83: 11.18 | N83: pitchbook | O83: 0 | P83: yfinance | Q83: -0.0009 | R83: pitchbook | AH83: =IFERROR(VLOOKUP($A83,fund_metadata!$A:$P,2,FALSE),"") -> Carlyle Alpinvest | AI83: =IFERROR(VLOOKUP($A83,fund_metadata!$A:$P,16,FALSE),"") -> private_equity
A84: 2 | B84: 45199 | K84: 255740000 | L84: pitchbook | M84: 11.56 | N84: pitchbook | O84: 0 | P84: yfinance | Q84: 0.0339 | R84: pitchbook | S84: 132 | V84: 22123474 | W84: N-CSRS | AH84: =IFERROR(VLOOKUP($A84,fund_metadata!$A:$P,2,FALSE),"") -> Carlyle Alpinvest | AI84: =IFERROR(VLOOKUP($A84,fund_metadata!$A:$P,16,FALSE),"") -> private_equity
A85: 2 | B85: 45230 | K85: 260590000 | L85: pitchbook | M85: 11.44 | N85: pitchbook | O85: 0 | P85: yfinance | Q85: -0.0103 | R85: pitchbook | AH85: =IFERROR(VLOOKUP($A85,fund_metadata!$A:$P,2,FALSE),"") -> Carlyle Alpinvest | AI85: =IFERROR(VLOOKUP($A85,fund_metadata!$A:$P,16,FALSE),"") -> private_equity
A86: 2 | B86: 45260 | K86: 282750000 | L86: pitchbook | M86: 11.48 | N86: pitchbook | O86: 0 | P86: yfinance | Q86: 0.0035 | R86: pitchbook | AH86: =IFERROR(VLOOKUP($A86,fund_metadata!$A:$P,2,FALSE),"") -> Carlyle Alpinvest | AI86: =IFERROR(VLOOKUP($A86,fund_metadata!$A:$P,16,FALSE),"") -> private_equity
A87: 2 | B87: 45291 | K87: 311630000 | L87: pitchbook | M87: 11.73 | N87: pitchbook | O87: 0 | P87: yfinance | Q87: 0.0236 | R87: pitchbook | S87: 157 | AH87: =IFERROR(VLOOKUP($A87,fund_metadata!$A:$P,2,FALSE),"") -> Carlyle Alpinvest | AI87: =IFERROR(VLOOKUP($A87,fund_metadata!$A:$P,16,FALSE),"") -> private_equity
A88: 2 | B88: 45322 | K88: 357360000 | L88: pitchbook | M88: 11.88 | N88: pitchbook | O88: 0 | P88: yfinance | Q88: 0.0128 | R88: pitchbook | AH88: =IFERROR(VLOOKUP($A88,fund_metadata!$A:$P,2,FALSE),"") -> Carlyle Alpinvest | AI88: =IFERROR(VLOOKUP($A88,fund_metadata!$A:$P,16,FALSE),"") -> private_equity
A89: 2 | B89: 45351 | K89: 393340000 | L89: pitchbook | M89: 11.98 | N89: pitchbook | O89: 0 | P89: yfinance | Q89: 0.0084 | R89: pitchbook | AH89: =IFERROR(VLOOKUP($A89,fund_metadata!$A:$P,2,FALSE),"") -> Carlyle Alpinvest | AI89: =IFERROR(VLOOKUP($A89,fund_metadata!$A:$P,16,FALSE),"") -> private_equity
A90: 2 | B90: 45382 | K90: 439700000 | L90: pitchbook | M90: 12.17 | N90: pitchbook | O90: 0 | P90: yfinance | Q90: 0.0159 | R90: pitchbook | S90: 162 | V90: 36141096 | W90: N-CSR | AH90: =IFERROR(VLOOKUP($A90,fund_metadata!$A:$P,2,FALSE),"") -> Carlyle Alpinvest | AI90: =IFERROR(VLOOKUP($A90,fund_metadata!$A:$P,16,FALSE),"") -> private_equity
A91: 2 | B91: 45412 | K91: 476210000 | L91: pitchbook | M91: 12.17 | N91: pitchbook | O91: 0 | P91: yfinance | Q91: 0 | R91: pitchbook | AH91: =IFERROR(VLOOKUP($A91,fund_metadata!$A:$P,2,FALSE),"") -> Carlyle Alpinvest | AI91: =IFERROR(VLOOKUP($A91,fund_metadata!$A:$P,16,FALSE),"") -> private_equity
A92: 2 | B92: 45443 | K92: 523910000 | L92: pitchbook | M92: 12.03 | N92: pitchbook | O92: 0 | P92: yfinance | Q92: -0.0115 | R92: pitchbook | AH92: =IFERROR(VLOOKUP($A92,fund_metadata!$A:$P,2,FALSE),"") -> Carlyle Alpinvest | AI92: =IFERROR(VLOOKUP($A92,fund_metadata!$A:$P,16,FALSE),"") -> private_equity
A93: 2 | B93: 45473 | K93: 614060000 | L93: pitchbook | M93: 12.55 | N93: pitchbook | O93: 0 | P93: yfinance | Q93: 0.0432 | R93: pitchbook | S93: 180 | AH93: =IFERROR(VLOOKUP($A93,fund_metadata!$A:$P,2,FALSE),"") -> Carlyle Alpinvest | AI93: =IFERROR(VLOOKUP($A93,fund_metadata!$A:$P,16,FALSE),"") -> private_equity
A94: 2 | B94: 45504 | K94: 683190000 | L94: pitchbook | M94: 12.64 | N94: pitchbook | O94: 0 | P94: yfinance | Q94: 0.0072 | R94: pitchbook | AH94: =IFERROR(VLOOKUP($A94,fund_metadata!$A:$P,2,FALSE),"") -> Carlyle Alpinvest | AI94: =IFERROR(VLOOKUP($A94,fund_metadata!$A:$P,16,FALSE),"") -> private_equity
A95: 2 | B95: 45535 | K95: 798380000 | L95: pitchbook | M95: 12.99 | N95: pitchbook | Q95: 0.0277 | R95: pitchbook | AH95: =IFERROR(VLOOKUP($A95,fund_metadata!$A:$P,2,FALSE),"") -> Carlyle Alpinvest | AI95: =IFERROR(VLOOKUP($A95,fund_metadata!$A:$P,16,FALSE),"") -> private_equity
A96: 2 | B96: 45565 | K96: 916970000 | L96: pitchbook | M96: 13.23 | N96: pitchbook | Q96: 0.0185 | R96: pitchbook | S96: 201 | T96: 986410000 | U96: pitchbook | V96: 64327455 | W96: N-CSRS | AH96: =IFERROR(VLOOKUP($A96,fund_metadata!$A:$P,2,FALSE),"") -> Carlyle Alpinvest | AI96: =IFERROR(VLOOKUP($A96,fund_metadata!$A:$P,16,FALSE),"") -> private_equity
A97: 2 | B97: 45596 | K97: 1040000000 | L97: pitchbook | M97: 13.26 | N97: pitchbook | Q97: 0.0023 | R97: pitchbook | AH97: =IFERROR(VLOOKUP($A97,fund_metadata!$A:$P,2,FALSE),"") -> Carlyle Alpinvest | AI97: =IFERROR(VLOOKUP($A97,fund_metadata!$A:$P,16,FALSE),"") -> private_equity
A98: 2 | B98: 45626 | K98: 1190000000 | L98: pitchbook | M98: 13.27 | N98: pitchbook | Q98: 0.0008 | R98: pitchbook | AH98: =IFERROR(VLOOKUP($A98,fund_metadata!$A:$P,2,FALSE),"") -> Carlyle Alpinvest | AI98: =IFERROR(VLOOKUP($A98,fund_metadata!$A:$P,16,FALSE),"") -> private_equity
A99: 2 | B99: 45657 | K99: 1350000000 | L99: pitchbook | M99: 13.65 | N99: pitchbook | O99: 0.03 | P99: pitchbook | Q99: 0.0305 | R99: pitchbook | S99: 237 | AH99: =IFERROR(VLOOKUP($A99,fund_metadata!$A:$P,2,FALSE),"") -> Carlyle Alpinvest | AI99: =IFERROR(VLOOKUP($A99,fund_metadata!$A:$P,16,FALSE),"") -> private_equity
A100: 2 | B100: 45688 | K100: 1530000000 | L100: pitchbook | M100: 13.89 | N100: pitchbook | Q100: 0.0176 | R100: pitchbook | AH100: =IFERROR(VLOOKUP($A100,fund_metadata!$A:$P,2,FALSE),"") -> Carlyle Alpinvest | AI100: =IFERROR(VLOOKUP($A100,fund_metadata!$A:$P,16,FALSE),"") -> private_equity
...

Sheet pivot
B3: fund_id | C3: month_end | D3: monthly_return | E3: sgg_nav | F3: nav_per_share
B4: 1 | D4: 0.011815493 | E4: 20401211 | F4: 41.856438
B5: 2 | D5: 0.012669231 | E5: 10154379 | F5: 12.136
B6: 3 | D6: 0.0096465517 | E6: 38468270 | F6: 10.800667
B7: 4 | D7: 0.0131625 | E7: 30569224
B8: 5 | D8: 0.0070173913 | E8: 24655005 | F8: 10.1652
B9: 6 | D9: 0.014418182 | E9: 50253288 | F9: 47.998676
B10: 7 | D10: 0.021395238 | E10: 21528691 | F10: 39.979535
B11: 8 | D11: 0.0098515873 | E11: 39978754 | F11: 18.116614
B12: 9 | D12: 0.014194118 | E12: 40446746
B13: 10 | D13: 0.012490476 | E13: 40588235 | F13: 14.90375
B14: 11 | D14: 0.01225625 | E14: 40201307 | F14: 15.513333
B15: Grand Total | D15: 0.012266845 | E15: 3.5724511e+08 | F15: 24.993098

Sheet fund_metadata
A1: fund_id | B1: fund_name | C1: class_inception_date | D1: ticker | E1: cik | F1: share_class_count | G1: sec_name | H1: fund_type | I1: yfinance_link | J1: share_class | K1: direct_statement_name | L1: icapital_name | M1: ms_name | N1: website_link | O1: sgg_holding | P1: strategy | Q1: management_fee | R1: expense_ratio | S1: incentive_fee | T1: gate
A2: 1 | B2: Bow River Evergreen PE | C2: 44196 | D2: EVERX | E2: 1810256 | F2: 2 | G2: Bow River Capital Evergreen Fund | H2: Interval | I2: https://finance.yahoo.com/quote/EVERX/ | J2: Class I | K2: BOW RIVER CAP EVERGREEN FD CL I | N2: https://www.bowriverevergreen.com/ | O2: y | P2: private_equity | Q2: 0.0175 | R2: 0.0299 | T2: 0.05
A3: 2 | B3: Carlyle Alpinvest | C3: 45294 | D3: XCPIX | E3: 1899610 | F3: 4 | G3: Carlyle AlpInvest Private Markets Fund | H3: Tender | I3: https://finance.yahoo.com/quote/XCPIX/ | J3: Class I | K3: Carlyle Alphinvest Prvte Mrkts I | N3: https://www.carlyle.com/capm | O3: y | P3: private_equity | Q3: 0.0125 | R3: 0.0324 | S3: 0.1 | T3: 0.05
A4: 3 | B4: Cliffwater | C4: 44377 | D4: CELFX | E4: 1842754 | F4: 1 | G4: Cliffwater Enhanced Lending Fund | H4: Interval | I4: https://finance.yahoo.com/quote/CELFX/ | J4: Class I | K4: CLIFFWATER ENHANCED LENDING FUND CL I | N4: https://www.cliffwaterfunds.com/celfx | O4: y | P4: private_credit | Q4: 0.0095 | T4: 0.05
A5: 4 | B5: Coller Secondaries | C5: 45383 | E5: 1969180 | F5: 3 | G5: Coller Secondaries Private Equity Opportunities Fund | H5: Tender | J5: Class I | K5: Coller Secondaries Private Equity Opportunities Fund | N5: https://cspef.com/ | O5: y | P5: secondaries | Q5: 0.0165 | T5: 0.05
A6: 5 | B6: Stepstone PC Income | C6: 45446 | D6: CRDEX | E6: 2006100 | F6: 4 | G6: StepStone Private Credit Income Fund | H6: Interval | I6: https://finance.yahoo.com/quote/CRDEX/history/ | J6: Class I | K6: STEPSTONE PRIVATE CREDIT INCOME FD CL I | N6: https://www.stepstonegroup.com/what-we-do/solutions-services/private-wealth-solutions/crdex/ | O6: y | P6: private_credit | Q6: 0.0115 | T6: 0.05
A7: 6 | B7: Stepstone Private Markets | C7: 44105 | D7: XPMIX | E7: 1789470 | F7: 3 | G7: StepStone Private Markets | H7: Tender | I7: https://finance.yahoo.com/quote/XPMIX/ | J7: Class I | K7: STEPSTONE PRIVATE MARKETS I | N7: https://www.stepstonegroup.com/what-we-do/solutions-services/private-wealth-solutions/sprim/ | O7: y | P7: secondaries | Q7: 0.014 | T7: 0.05
A8: 7 | B8: Stepstone PV/Growth | C8: 44866 | D8: XSPIX | E8: 1918642 | F8: 3 | G8: StepStone Private Venture and Growth Fund | H8: Tender | I8: https://finance.yahoo.com/quote/XSPIX/ | J8: Class I | K8: STEPSTONE PRIVATE VENTURE AND GROWTH FD CL I | N8: https://www.stepstonegroup.com/what-we-do/solutions-services/private-wealth-solutions/spring/ | O8: y | P8: venture | Q8: 0.015 | T8: 0.025
A9: 8 | B9: AMG Pantheon | C9: 42304 | D9: XPEIX | E9: 1609211 | F9: 1 | G9: AMG Pantheon Fund, LLC | H9: Tender | J9: Class 3 | L9: AMG PANTHEON FUND CLASS 3 | M9: AMG PANTHEON FUND, LLC ESC | N9: https://www.pantheon.com/private-wealth-overview/amg-pantheon-fund/ | O9: y | P9: secondaries | Q9: 0.0125 | T9: 0.05
A10: 9 | B10: FLEX | C10: 45646 | E10: 2008602 | F10: 4 | G10: Franklin Lexington Private Markets Fund | H10: Tender | J10: Class I | M10: FLEX - CLASS I ESC | N10: https://www.flexpe.com | O10: y | P10: secondaries | Q10: 0.0125 | T10: 0.05
A11: 10 | B11: Hamilton Lane | C11: 44200 | D11: XHLIX | E11: 1803491 | F11: 3 | G11: Hamilton Lane Private Assets Fund | H11: Tender | I11: https://finance.yahoo.com/quote/XHLIX/ | J11: Class I | L11: HAMILTON LANE PVT ASSET FUND CL I | M11: HAMILTON LANE PAF (I) ESC | N11: https://www.hamiltonlane.com/en-us/strategies/evergreen/us-private-wealth/private-assets-fund | O11: y | P11: private_equity | Q11: 0.014 | R11: 0.0338 | S11: 0.1 | T11: 0.05
A12: 11 | B12: JPMF | C12: 45119 | E12: 1940499 | F12: 3 | G12: JPMorgan Private Markets Fund | H12: Tender | J12: Class I | L12: JPMORGAN PRIVATE MARKETS FUND - I | M12: JPMF CLASS I ESC | N12: https://am.jpmorgan.com/us/en/asset-management/adv/products/jpmorgan-private-markets-fund-i-48130f306 | O12: y | P12: private_equity | Q12: 0.01 | T12: 0.05

Sheet pitchbook_index
A1: month_end | B1: pitchbook_index
A2: 41820 | B2: 100
A3: 41851 | B3: 99.922618
A4: 41882 | B4: 100.48179
A5: 41912 | B5: 100.70548
A6: 41943 | B6: 101.05813
A7: 41973 | B7: 101.53131
A8: 42004 | B8: 100.99359
A9: 42035 | B9: 101.15965
A10: 42063 | B10: 102.68618
A11: 42094 | B11: 103.68794
A12: 42124 | B12: 104.06627
A13: 42155 | B13: 104.49655
... A139: 45991 | B139: 219.95068

Sheet stepstone_pm_index
A1: month_end | B1: steptone_pm_index
A2: 38807 | B2: 1000
A3: 38810 | B3: 1000.13
A4: 38811 | B4: 1001.46
A5: 38812 | B5: 1001.53
A6: 38813 | B6: 1001.25
A7: 38814 | B7: 1000.23
A8: 38817 | B8: 1000.16
A9: 38818 | B9: 1000.39
A10: 38819 | B10: 1000.26
A11: 38820 | B11: 1000.05
A12: 38824 | B12: 1001.82
A13: 38825 | B13: 1001.85
... A5026: 46175 | B5026: 7101.73

Sheet sp500_index
A1: month_end | B1: sp500_index
A2: 36556 | B2: 1394.46
A3: 36585 | B3: 1366.42
A4: 36616 | B4: 1498.58
A5: 36646 | B5: 1452.4301
A6: 36677 | B6: 1420.6
A7: 36707 | B7: 1454.6
A8: 36738 | B8: 1430.83
A9: 36769 | B9: 1517.6801
A10: 36799 | B10: 1436.51
A11: 36830 | B11: 1429.4
A12: 36860 | B12: 1314.95
A13: 36891 | B13: 1320.28
... A319: 46203 | B319: 7266.9902
